{
"meta":{"test_sets":[],"test_metrics":[],"learn_metrics":[{"best_value":"Min","name":"RMSE"}],"launch_mode":"Train","parameters":"","iteration_count":1000,"learn_sets":["learn"],"name":"experiment"},
"iterations":[
{"learn":[14.59871775],"iteration":0,"passed_time":0.0594221447,"remaining_time":59.36272255},
{"learn":[14.22518863],"iteration":1,"passed_time":0.05978289709,"remaining_time":29.83166565},
{"learn":[13.8866124],"iteration":2,"passed_time":0.06008473243,"remaining_time":19.96815941},
{"learn":[13.52356875],"iteration":3,"passed_time":0.06036410929,"remaining_time":15.03066321},
{"learn":[13.18870211],"iteration":4,"passed_time":0.06063990278,"remaining_time":12.06734065},
{"learn":[12.9124226],"iteration":5,"passed_time":0.06095302986,"remaining_time":10.09788528},
{"learn":[12.60003351],"iteration":6,"passed_time":0.06129103211,"remaining_time":8.694570698},
{"learn":[12.32990573],"iteration":7,"passed_time":0.06156274225,"remaining_time":7.633780039},
{"learn":[12.0660619],"iteration":8,"passed_time":0.06192457798,"remaining_time":6.818584087},
{"learn":[11.77309809],"iteration":9,"passed_time":0.06215374617,"remaining_time":6.153220871},
{"learn":[11.49227636],"iteration":10,"passed_time":0.06241228956,"remaining_time":5.611432216},
{"learn":[11.26264833],"iteration":11,"passed_time":0.06269849979,"remaining_time":5.162176483},
{"learn":[11.04260393],"iteration":12,"passed_time":0.06299112673,"remaining_time":4.782480161},
{"learn":[10.79916926],"iteration":13,"passed_time":0.06324371175,"remaining_time":4.45416427},
{"learn":[10.5541002],"iteration":14,"passed_time":0.06348233833,"remaining_time":4.16867355},
{"learn":[10.31918115],"iteration":15,"passed_time":0.0637983821,"remaining_time":3.923600499},
{"learn":[10.10004441],"iteration":16,"passed_time":0.06407696728,"remaining_time":3.705156402},
{"learn":[9.894556723],"iteration":17,"passed_time":0.06435209411,"remaining_time":3.510764245},
{"learn":[9.690174082],"iteration":18,"passed_time":0.06464142936,"remaining_time":3.337539063},
{"learn":[9.506034866],"iteration":19,"passed_time":0.0650535571,"remaining_time":3.187624298},
{"learn":[9.338524633],"iteration":20,"passed_time":0.06532851726,"remaining_time":3.045553257},
{"learn":[9.170203312],"iteration":21,"passed_time":0.06614598102,"remaining_time":2.94048952},
{"learn":[9.010299969],"iteration":22,"passed_time":0.06639298266,"remaining_time":2.820258437},
{"learn":[8.843866678],"iteration":23,"passed_time":0.06663544261,"remaining_time":2.709841333},
{"learn":[8.690548059],"iteration":24,"passed_time":0.06688290258,"remaining_time":2.608433201},
{"learn":[8.555307687],"iteration":25,"passed_time":0.06713827928,"remaining_time":2.515103232},
{"learn":[8.413851302],"iteration":26,"passed_time":0.06739503099,"remaining_time":2.428717228},
{"learn":[8.29256019],"iteration":27,"passed_time":0.06762099082,"remaining_time":2.347414396},
{"learn":[8.162193833],"iteration":28,"passed_time":0.06783036721,"remaining_time":2.271147812},
{"learn":[8.040736294],"iteration":29,"passed_time":0.06806820212,"remaining_time":2.200871869},
{"learn":[7.921220278],"iteration":30,"passed_time":0.06831716211,"remaining_time":2.135462261},
{"learn":[7.809589039],"iteration":31,"passed_time":0.0686108724,"remaining_time":2.07547889},
{"learn":[7.699675801],"iteration":32,"passed_time":0.06889558262,"remaining_time":2.018849345},
{"learn":[7.60645267],"iteration":33,"passed_time":0.06917425114,"remaining_time":1.965362547},
{"learn":[7.498880302],"iteration":34,"passed_time":0.06946291972,"remaining_time":1.915191929},
{"learn":[7.401158744],"iteration":35,"passed_time":0.06972396312,"remaining_time":1.86705279},
{"learn":[7.306431077],"iteration":36,"passed_time":0.06996313138,"remaining_time":1.820932311},
{"learn":[7.223863468],"iteration":37,"passed_time":0.07025304997,"remaining_time":1.778511423},
{"learn":[7.143477682],"iteration":38,"passed_time":0.07056784373,"remaining_time":1.738864047},
{"learn":[7.062817131],"iteration":39,"passed_time":0.0709549713,"remaining_time":1.702919311},
{"learn":[6.990793435],"iteration":40,"passed_time":0.07126572336,"remaining_time":1.666922651},
{"learn":[6.931862224],"iteration":41,"passed_time":0.07153989185,"remaining_time":1.631790866},
{"learn":[6.858296558],"iteration":42,"passed_time":0.07180410194,"remaining_time":1.598058734},
{"learn":[6.786268161],"iteration":43,"passed_time":0.07207147871,"remaining_time":1.565916674},
{"learn":[6.717118549],"iteration":44,"passed_time":0.07238614747,"remaining_time":1.536194907},
{"learn":[6.652948106],"iteration":45,"passed_time":0.07279865021,"remaining_time":1.509780702},
{"learn":[6.589686076],"iteration":46,"passed_time":0.07310894394,"remaining_time":1.482400502},
{"learn":[6.531283097],"iteration":47,"passed_time":0.0733933625,"remaining_time":1.455635023},
{"learn":[6.471368031],"iteration":48,"passed_time":0.0736399058,"remaining_time":1.429215315},
{"learn":[6.416481395],"iteration":49,"passed_time":0.07393478276,"remaining_time":1.404760872},
{"learn":[6.369870822],"iteration":50,"passed_time":0.07419120113,"remaining_time":1.380538233},
{"learn":[6.325678067],"iteration":51,"passed_time":0.07447128632,"remaining_time":1.357668835},
{"learn":[6.275766122],"iteration":52,"passed_time":0.07479495514,"remaining_time":1.336430614},
{"learn":[6.224773967],"iteration":53,"passed_time":0.07507024863,"remaining_time":1.315119541},
{"learn":[6.182249254],"iteration":54,"passed_time":0.0753365004,"remaining_time":1.294418052},
{"learn":[6.139904173],"iteration":55,"passed_time":0.07557654366,"remaining_time":1.274004593},
{"learn":[6.100525536],"iteration":56,"passed_time":0.07583171202,"remaining_time":1.254549201},
{"learn":[6.062568564],"iteration":57,"passed_time":0.07606742192,"remaining_time":1.235439853},
{"learn":[6.030559288],"iteration":58,"passed_time":0.07628200668,"remaining_time":1.216633361},
{"learn":[5.997931376],"iteration":59,"passed_time":0.0765202166,"remaining_time":1.198816727},
{"learn":[5.964103835],"iteration":60,"passed_time":0.07674446809,"remaining_time":1.181361566},
{"learn":[5.933729724],"iteration":61,"passed_time":0.0770676369,"remaining_time":1.165958765},
{"learn":[5.901932711],"iteration":62,"passed_time":0.0773136802,"remaining_time":1.149887593},
{"learn":[5.873727795],"iteration":63,"passed_time":0.07755647348,"remaining_time":1.134263425},
{"learn":[5.846485734],"iteration":64,"passed_time":0.07788751735,"remaining_time":1.12038198},
{"learn":[5.820630862],"iteration":65,"passed_time":0.07812335225,"remaining_time":1.105563803},
{"learn":[5.793646238],"iteration":66,"passed_time":0.07843377097,"remaining_time":1.092219527},
{"learn":[5.765388646],"iteration":67,"passed_time":0.0787179812,"remaining_time":1.078899389},
{"learn":[5.747073912],"iteration":68,"passed_time":0.07960632043,"remaining_time":1.074108468},
{"learn":[5.722315217],"iteration":69,"passed_time":0.07990165572,"remaining_time":1.061550569},
{"learn":[5.699970599],"iteration":70,"passed_time":0.0801842826,"remaining_time":1.04917181},
{"learn":[5.682732647],"iteration":71,"passed_time":0.08047407619,"remaining_time":1.037221426},
{"learn":[5.663525791],"iteration":72,"passed_time":0.08079495332,"remaining_time":1.025985229},
{"learn":[5.642381613],"iteration":73,"passed_time":0.0810924553,"remaining_time":1.014751535},
{"learn":[5.621404779],"iteration":74,"passed_time":0.08143287423,"remaining_time":1.004338782},
{"learn":[5.602460129],"iteration":75,"passed_time":0.08165587571,"remaining_time":0.9927635415},
{"learn":[5.587337574],"iteration":76,"passed_time":0.08194508596,"remaining_time":0.9822768097},
{"learn":[5.572393026],"iteration":77,"passed_time":0.08215875405,"remaining_time":0.9711586056},
{"learn":[5.558425806],"iteration":78,"passed_time":0.08251338141,"remaining_time":0.9619598009},
{"learn":[5.541518902],"iteration":79,"passed_time":0.08276088305,"remaining_time":0.9517501551},
{"learn":[5.526157283],"iteration":80,"passed_time":0.08302730149,"remaining_time":0.9420011119},
{"learn":[5.511746977],"iteration":81,"passed_time":0.08326451139,"remaining_time":0.9321563593},
{"learn":[5.504975022],"iteration":82,"passed_time":0.0833763038,"remaining_time":0.921157477},
{"learn":[5.493980522],"iteration":83,"passed_time":0.08377909815,"remaining_time":0.9135911179},
{"learn":[5.480745463],"iteration":84,"passed_time":0.08406622505,"remaining_time":0.9049481873},
{"learn":[5.464052013],"iteration":85,"passed_time":0.08436314369,"remaining_time":0.8966036434},
{"learn":[5.449143727],"iteration":86,"passed_time":0.08461277035,"remaining_time":0.8879478084},
{"learn":[5.438255432],"iteration":87,"passed_time":0.0848664387,"remaining_time":0.8795249102},
{"learn":[5.425927931],"iteration":88,"passed_time":0.08513110713,"remaining_time":0.8713981864},
{"learn":[5.412331217],"iteration":89,"passed_time":0.08533556682,"remaining_time":0.8628373978},
{"learn":[5.400691499],"iteration":90,"passed_time":0.08557027671,"remaining_time":0.8547624344},
{"learn":[5.391618744],"iteration":91,"passed_time":0.08657795007,"remaining_time":0.8544867246},
{"learn":[5.380766572],"iteration":92,"passed_time":0.08680136822,"remaining_time":0.8465466772},
{"learn":[5.372207183],"iteration":93,"passed_time":0.08710657858,"remaining_time":0.839559151},
{"learn":[5.362918837],"iteration":94,"passed_time":0.08739920553,"remaining_time":0.8325924316},
{"learn":[5.348292324],"iteration":95,"passed_time":0.08761841531,"remaining_time":0.8250734109},
{"learn":[5.339772295],"iteration":96,"passed_time":0.0878520002,"remaining_time":0.8178387235},
{"learn":[5.331515983],"iteration":97,"passed_time":0.08813554375,"remaining_time":0.8112067394},
{"learn":[5.323861644],"iteration":98,"passed_time":0.08838421207,"remaining_time":0.8043856068},
{"learn":[5.313277281],"iteration":99,"passed_time":0.08887129864,"remaining_time":0.7998416877},
{"learn":[5.30685627],"iteration":100,"passed_time":0.08923205103,"remaining_time":0.7942536028},
{"learn":[5.29652059],"iteration":101,"passed_time":0.08947546932,"remaining_time":0.7877350142},
{"learn":[5.288350766],"iteration":102,"passed_time":0.08976617958,"remaining_time":0.781750127},
{"learn":[5.27993346],"iteration":103,"passed_time":0.09007930666,"remaining_time":0.7760678728},
{"learn":[5.271789139],"iteration":104,"passed_time":0.09038464202,"remaining_time":0.7704214725},
{"learn":[5.262684686],"iteration":105,"passed_time":0.09064835211,"remaining_time":0.764524781},
{"learn":[5.251619772],"iteration":106,"passed_time":0.0908783953,"remaining_time":0.7584524019},
{"learn":[5.241012171],"iteration":107,"passed_time":0.09122985597,"remaining_time":0.7534910326},
{"learn":[5.232684032],"iteration":108,"passed_time":0.09149219104,"remaining_time":0.7478857084},
{"learn":[5.224267141],"iteration":109,"passed_time":0.09176581786,"remaining_time":0.74246889},
{"learn":[5.216324968],"iteration":110,"passed_time":0.09207056989,"remaining_time":0.7373940237},
{"learn":[5.211102527],"iteration":111,"passed_time":0.09228907134,"remaining_time":0.7317204942},
{"learn":[5.206364257],"iteration":112,"passed_time":0.09251028114,"remaining_time":0.7261647732},
{"learn":[5.196937641],"iteration":113,"passed_time":0.092740491,"remaining_time":0.720772588},
{"learn":[5.190746047],"iteration":114,"passed_time":0.0930508264,"remaining_time":0.7160867945},
{"learn":[5.181885213],"iteration":115,"passed_time":0.09343353727,"remaining_time":0.7120279909},
{"learn":[5.178293568],"iteration":116,"passed_time":0.09373416427,"remaining_time":0.7074125389},
{"learn":[5.170991438],"iteration":117,"passed_time":0.09402279119,"remaining_time":0.702780524},
{"learn":[5.166257212],"iteration":118,"passed_time":0.09430204304,"remaining_time":0.6981521002},
{"learn":[5.161421246],"iteration":119,"passed_time":0.0945772532,"remaining_time":0.6935665235},
{"learn":[5.158223542],"iteration":120,"passed_time":0.09480596306,"remaining_time":0.6887143928},
{"learn":[5.15470988],"iteration":121,"passed_time":0.0957056357,"remaining_time":0.6887667881},
{"learn":[5.146388143],"iteration":122,"passed_time":0.0959722208,"remaining_time":0.6842897369},
{"learn":[5.139529364],"iteration":123,"passed_time":0.09622538915,"remaining_time":0.6797858137},
{"learn":[5.134276023],"iteration":124,"passed_time":0.09647322413,"remaining_time":0.6753125689},
{"learn":[5.128536065],"iteration":125,"passed_time":0.09678143451,"remaining_time":0.6713251886},
{"learn":[5.123300353],"iteration":126,"passed_time":0.09696985243,"remaining_time":0.6665722927},
{"learn":[5.116200518],"iteration":127,"passed_time":0.09721535406,"remaining_time":0.6622795995},
{"learn":[5.108728704],"iteration":128,"passed_time":0.09750456431,"remaining_time":0.6583447715},
{"learn":[5.104075866],"iteration":129,"passed_time":0.097758441,"remaining_time":0.6542295667},
{"learn":[5.100317606],"iteration":130,"passed_time":0.09797335909,"remaining_time":0.6499148783},
{"learn":[5.095814182],"iteration":131,"passed_time":0.09828336115,"remaining_time":0.6462875567},
{"learn":[5.092146915],"iteration":132,"passed_time":0.0984964459,"remaining_time":0.6420783353},
{"learn":[5.085258329],"iteration":133,"passed_time":0.09876586436,"remaining_time":0.6382928249},
{"learn":[5.079219421],"iteration":134,"passed_time":0.09899153252,"remaining_time":0.6342790788},
{"learn":[5.076476829],"iteration":135,"passed_time":0.09919686722,"remaining_time":0.6301918623},
{"learn":[5.072133867],"iteration":136,"passed_time":0.09956861969,"remaining_time":0.6272096262},
{"learn":[5.067031564],"iteration":137,"passed_time":0.09983678814,"remaining_time":0.6236181984},
{"learn":[5.061358312],"iteration":138,"passed_time":0.1001240817,"remaining_time":0.6201930529},
{"learn":[5.056759124],"iteration":139,"passed_time":0.1004294171,"remaining_time":0.616923562},
{"learn":[5.050254],"iteration":140,"passed_time":0.100661627,"remaining_time":0.6132506209},
{"learn":[5.048376474],"iteration":141,"passed_time":0.1008181697,"remaining_time":0.6091689406},
{"learn":[5.042603751],"iteration":142,"passed_time":0.1011000465,"remaining_time":0.6058932858},
{"learn":[5.037477349],"iteration":143,"passed_time":0.1013907151,"remaining_time":0.6027114733},
{"learn":[5.03230489],"iteration":144,"passed_time":0.1016360084,"remaining_time":0.5993019807},
{"learn":[5.025976187],"iteration":145,"passed_time":0.1019180936,"remaining_time":0.5961510408},
{"learn":[5.01952451],"iteration":146,"passed_time":0.1030197676,"remaining_time":0.5977949781},
{"learn":[5.017569424],"iteration":147,"passed_time":0.1033615199,"remaining_time":0.595027128},
{"learn":[5.008962367],"iteration":148,"passed_time":0.1036166466,"remaining_time":0.5917970888},
{"learn":[5.003880266],"iteration":149,"passed_time":0.1038478564,"remaining_time":0.5884711865},
{"learn":[4.996387564],"iteration":150,"passed_time":0.1041585668,"remaining_time":0.5856332666},
{"learn":[4.993361683],"iteration":151,"passed_time":0.1044675689,"remaining_time":0.5828190686},
{"learn":[4.99005752],"iteration":152,"passed_time":0.1047217373,"remaining_time":0.5797340618},
{"learn":[4.986908764],"iteration":153,"passed_time":0.1050012808,"remaining_time":0.5768252178},
{"learn":[4.985207175],"iteration":154,"passed_time":0.105280866,"remaining_time":0.5739505274},
{"learn":[4.979003494],"iteration":155,"passed_time":0.1056016598,"remaining_time":0.5713320567},
{"learn":[4.973142217],"iteration":156,"passed_time":0.1058729116,"remaining_time":0.5684768436},
{"learn":[4.967056696],"iteration":157,"passed_time":0.1061502467,"remaining_time":0.5656867579},
{"learn":[4.961460696],"iteration":158,"passed_time":0.1064339986,"remaining_time":0.5629622191},
{"learn":[4.954240363],"iteration":159,"passed_time":0.1067140838,"remaining_time":0.56024894},
{"learn":[4.952320707],"iteration":160,"passed_time":0.1069042101,"remaining_time":0.5570970948},
{"learn":[4.948337777],"iteration":161,"passed_time":0.1071350866,"remaining_time":0.5541926085},
{"learn":[4.943228639],"iteration":162,"passed_time":0.1074462137,"remaining_time":0.5517330114},
{"learn":[4.938545759],"iteration":163,"passed_time":0.1077259655,"remaining_time":0.549139678},
{"learn":[4.935330572],"iteration":164,"passed_time":0.1079633421,"remaining_time":0.5463599434},
{"learn":[4.932051543],"iteration":165,"passed_time":0.1083593864,"remaining_time":0.5444080016},
{"learn":[4.928964153],"iteration":166,"passed_time":0.1087373056,"remaining_time":0.5423842848},
{"learn":[4.922860227],"iteration":167,"passed_time":0.1090381409,"remaining_time":0.5399984122},
{"learn":[4.917668772],"iteration":168,"passed_time":0.1093021427,"remaining_time":0.537456098},
{"learn":[4.910365386],"iteration":169,"passed_time":0.1095331025,"remaining_time":0.5347792654},
{"learn":[4.906457206],"iteration":170,"passed_time":0.1097849375,"remaining_time":0.5322322411},
{"learn":[4.901996508],"iteration":171,"passed_time":0.1100612311,"remaining_time":0.5298296472},
{"learn":[4.896816173],"iteration":172,"passed_time":0.1103226495,"remaining_time":0.5273805266},
{"learn":[4.891123132],"iteration":173,"passed_time":0.1105985263,"remaining_time":0.525025188},
{"learn":[4.887630202],"iteration":174,"passed_time":0.1109244451,"remaining_time":0.522929527},
{"learn":[4.885259712],"iteration":175,"passed_time":0.1112009053,"remaining_time":0.5206224202},
{"learn":[4.880659728],"iteration":176,"passed_time":0.1114662404,"remaining_time":0.5182865301},
{"learn":[4.877299723],"iteration":177,"passed_time":0.1117317838,"remaining_time":0.5159748668},
{"learn":[4.874038772],"iteration":178,"passed_time":0.1120588277,"remaining_time":0.5139681425},
{"learn":[4.86943698],"iteration":179,"passed_time":0.1124503303,"remaining_time":0.5122737267},
{"learn":[4.861268711],"iteration":180,"passed_time":0.1127705407,"remaining_time":0.5102711207},
{"learn":[4.858673056],"iteration":181,"passed_time":0.1130855011,"remaining_time":0.5082634062},
{"learn":[4.854036207],"iteration":182,"passed_time":0.1133080443,"remaining_time":0.5058615966},
{"learn":[4.85130244],"iteration":183,"passed_time":0.1135587959,"remaining_time":0.5036085733},
{"learn":[4.847510084],"iteration":184,"passed_time":0.1138315061,"remaining_time":0.5014739323},
{"learn":[4.845691673],"iteration":185,"passed_time":0.1140767994,"remaining_time":0.4992393264},
{"learn":[4.842058646],"iteration":186,"passed_time":0.1142889258,"remaining_time":0.4968818004},
{"learn":[4.838623675],"iteration":187,"passed_time":0.1145327191,"remaining_time":0.4946838718},
{"learn":[4.834602161],"iteration":188,"passed_time":0.114917055,"remaining_time":0.4931096909},
{"learn":[4.830858976],"iteration":189,"passed_time":0.1151863068,"remaining_time":0.491057413},
{"learn":[4.827590511],"iteration":190,"passed_time":0.1154986005,"remaining_time":0.4892061142},
{"learn":[4.822246226],"iteration":191,"passed_time":0.1157874774,"remaining_time":0.4872723008},
{"learn":[4.816686395],"iteration":192,"passed_time":0.1160053122,"remaining_time":0.4850584816},
{"learn":[4.814797121],"iteration":193,"passed_time":0.116333731,"remaining_time":0.4833246764},
{"learn":[4.811639392],"iteration":194,"passed_time":0.1166619832,"remaining_time":0.4816045974},
{"learn":[4.804813432],"iteration":195,"passed_time":0.1169540685,"remaining_time":0.4797503626},
{"learn":[4.80251613],"iteration":196,"passed_time":0.1172401954,"remaining_time":0.4778877},
{"learn":[4.800087884],"iteration":197,"passed_time":0.1176771566,"remaining_time":0.4766519173},
{"learn":[4.794773135],"iteration":198,"passed_time":0.1179431584,"remaining_time":0.4747360296},
{"learn":[4.791664833],"iteration":199,"passed_time":0.1182917441,"remaining_time":0.4731669762},
{"learn":[4.785989873],"iteration":200,"passed_time":0.1185349123,"remaining_time":0.4711910197},
{"learn":[4.782387142],"iteration":201,"passed_time":0.1188210809,"remaining_time":0.4694020919},
{"learn":[4.778623704],"iteration":202,"passed_time":0.1190668325,"remaining_time":0.4674692883},
{"learn":[4.775772178],"iteration":203,"passed_time":0.1193512928,"remaining_time":0.4657040639},
{"learn":[4.77023101],"iteration":204,"passed_time":0.1196857533,"remaining_time":0.4641471897},
{"learn":[4.764496689],"iteration":205,"passed_time":0.119943255,"remaining_time":0.4623055558},
{"learn":[4.763138716],"iteration":206,"passed_time":0.1202346736,"remaining_time":0.4606091603},
{"learn":[4.758053283],"iteration":207,"passed_time":0.1204925503,"remaining_time":0.4587985571},
{"learn":[4.755063788],"iteration":208,"passed_time":0.1207278436,"remaining_time":0.456917341},
{"learn":[4.752465267],"iteration":209,"passed_time":0.1210153455,"remaining_time":0.4552482044},
{"learn":[4.748067377],"iteration":210,"passed_time":0.121251347,"remaining_time":0.4533995868},
{"learn":[4.744163298],"iteration":211,"passed_time":0.1215047654,"remaining_time":0.4516309204},
{"learn":[4.736670896],"iteration":212,"passed_time":0.1218556427,"remaining_time":0.4502365766},
{"learn":[4.73349255],"iteration":213,"passed_time":0.1221149361,"remaining_time":0.4485156065},
{"learn":[4.731864595],"iteration":214,"passed_time":0.1225497723,"remaining_time":0.4474491688},
{"learn":[4.728398311],"iteration":215,"passed_time":0.1227856072,"remaining_time":0.4456662781},
{"learn":[4.723865975],"iteration":216,"passed_time":0.1230212755,"remaining_time":0.4438970447},
{"learn":[4.723483365],"iteration":217,"passed_time":0.1232764855,"remaining_time":0.4422119801},
{"learn":[4.72095416],"iteration":218,"passed_time":0.1236089877,"remaining_time":0.4408156137},
{"learn":[4.716173382],"iteration":219,"passed_time":0.1239538233,"remaining_time":0.4394726463},
{"learn":[4.710563974],"iteration":220,"passed_time":0.1242246585,"remaining_time":0.4378778685},
{"learn":[4.707160263],"iteration":221,"passed_time":0.1244524933,"remaining_time":0.4361443234},
{"learn":[4.70408351],"iteration":222,"passed_time":0.1247162867,"remaining_time":0.434549573},
{"learn":[4.702501831],"iteration":223,"passed_time":0.1251104977,"remaining_time":0.4334185098},
{"learn":[4.700269738],"iteration":224,"passed_time":0.1254382082,"remaining_time":0.4320649393},
{"learn":[4.695346302],"iteration":225,"passed_time":0.1256736681,"remaining_time":0.4304045093},
{"learn":[4.689769299],"iteration":226,"passed_time":0.1259138363,"remaining_time":0.4287726674},
{"learn":[4.687919514],"iteration":227,"passed_time":0.1261575463,"remaining_time":0.4271650252},
{"learn":[4.682982074],"iteration":228,"passed_time":0.1264711734,"remaining_time":0.4258046929},
{"learn":[4.679578702],"iteration":229,"passed_time":0.1266989666,"remaining_time":0.4241661054},
{"learn":[4.675751423],"iteration":230,"passed_time":0.1269542599,"remaining_time":0.4226312809},
{"learn":[4.672710726],"iteration":231,"passed_time":0.1272373451,"remaining_time":0.4211994874},
{"learn":[4.6690533],"iteration":232,"passed_time":0.1274846801,"remaining_time":0.4196598697},
{"learn":[4.667595702],"iteration":233,"passed_time":0.1278232657,"remaining_time":0.4184300065},
{"learn":[4.664241291],"iteration":234,"passed_time":0.1281129343,"remaining_time":0.4170484882},
{"learn":[4.662246999],"iteration":235,"passed_time":0.1283861444,"remaining_time":0.4156229422},
{"learn":[4.658668443],"iteration":236,"passed_time":0.1286604379,"remaining_time":0.4142106082},
{"learn":[4.658017572],"iteration":237,"passed_time":0.1289784817,"remaining_time":0.412947912},
{"learn":[4.657656705],"iteration":238,"passed_time":0.1292343584,"remaining_time":0.4114951747},
{"learn":[4.653242871],"iteration":239,"passed_time":0.1295700273,"remaining_time":0.4103050864},
{"learn":[4.6507302],"iteration":240,"passed_time":0.129878821,"remaining_time":0.4090374488},
{"learn":[4.647671336],"iteration":241,"passed_time":0.1300947808,"remaining_time":0.407486958},
{"learn":[4.645506007],"iteration":242,"passed_time":0.1304248246,"remaining_time":0.4063028488},
{"learn":[4.641297906],"iteration":243,"passed_time":0.1307870771,"remaining_time":0.4052255338},
{"learn":[4.63798107],"iteration":244,"passed_time":0.1310757873,"remaining_time":0.4039274262},
{"learn":[4.635062318],"iteration":245,"passed_time":0.1314945817,"remaining_time":0.4030362384},
{"learn":[4.631606017],"iteration":246,"passed_time":0.1318673342,"remaining_time":0.4020085128},
{"learn":[4.630215494],"iteration":247,"passed_time":0.1321048358,"remaining_time":0.4005759537},
{"learn":[4.62729814],"iteration":248,"passed_time":0.1324716716,"remaining_time":0.3995430737},
{"learn":[4.624691756],"iteration":249,"passed_time":0.1327282983,"remaining_time":0.3981848948},
{"learn":[4.621840053],"iteration":250,"passed_time":0.1330422587,"remaining_time":0.3970065807},
{"learn":[4.619602091],"iteration":251,"passed_time":0.1332873437,"remaining_time":0.3956306867},
{"learn":[4.613584029],"iteration":252,"passed_time":0.1336088458,"remaining_time":0.3944893589},
{"learn":[4.6119388],"iteration":253,"passed_time":0.1339147645,"remaining_time":0.3933087178},
{"learn":[4.60870702],"iteration":254,"passed_time":0.1341474744,"remaining_time":0.3919210526},
{"learn":[4.604771557],"iteration":255,"passed_time":0.1344215179,"remaining_time":0.3906625363},
{"learn":[4.604231277],"iteration":256,"passed_time":0.134690228,"remaining_time":0.3893962622},
{"learn":[4.600750354],"iteration":257,"passed_time":0.1349299796,"remaining_time":0.3880544374},
{"learn":[4.596488253],"iteration":258,"passed_time":0.1351840646,"remaining_time":0.3867621307},
{"learn":[4.59470784],"iteration":259,"passed_time":0.1354136911,"remaining_time":0.3854081978},
{"learn":[4.588818005],"iteration":260,"passed_time":0.1356799429,"remaining_time":0.3841665816},
{"learn":[4.585054174],"iteration":261,"passed_time":0.135954653,"remaining_time":0.3829562364},
{"learn":[4.581471435],"iteration":262,"passed_time":0.1362355716,"remaining_time":0.381770404},
{"learn":[4.577555199],"iteration":263,"passed_time":0.1364921149,"remaining_time":0.380523472},
{"learn":[4.57457145],"iteration":264,"passed_time":0.136856409,"remaining_time":0.3795828703},
{"learn":[4.573029224],"iteration":265,"passed_time":0.1371685778,"remaining_time":0.3785027672},
{"learn":[4.571326203],"iteration":266,"passed_time":0.137403871,"remaining_time":0.3772173687},
{"learn":[4.571019224],"iteration":267,"passed_time":0.1376696644,"remaining_time":0.3760231133},
{"learn":[4.565766631],"iteration":268,"passed_time":0.137908541,"remaining_time":0.3747626152},
{"learn":[4.563383471],"iteration":269,"passed_time":0.1382108764,"remaining_time":0.3736812583},
{"learn":[4.558165805],"iteration":270,"passed_time":0.1384837532,"remaining_time":0.3725264061},
{"learn":[4.55629209],"iteration":271,"passed_time":0.1387893802,"remaining_time":0.3714656941},
{"learn":[4.549383848],"iteration":272,"passed_time":0.1391566743,"remaining_time":0.3705747334},
{"learn":[4.546227503],"iteration":273,"passed_time":0.1394235927,"remaining_time":0.3694216363},
{"learn":[4.540620977],"iteration":274,"passed_time":0.1397310115,"remaining_time":0.3683817575},
{"learn":[4.532898237],"iteration":275,"passed_time":0.1401518059,"remaining_time":0.3676445923},
{"learn":[4.529757367],"iteration":276,"passed_time":0.1404081826,"remaining_time":0.3664805633},
{"learn":[4.52579294],"iteration":277,"passed_time":0.1407953102,"remaining_time":0.3656626401},
{"learn":[4.521572155],"iteration":278,"passed_time":0.1410553119,"remaining_time":0.3645192828},
{"learn":[4.518818099],"iteration":279,"passed_time":0.1412942718,"remaining_time":0.3633281276},
{"learn":[4.514012334],"iteration":280,"passed_time":0.1416320241,"remaining_time":0.3623965314},
{"learn":[4.508331416],"iteration":281,"passed_time":0.1419017759,"remaining_time":0.3612960109},
{"learn":[4.506038537],"iteration":282,"passed_time":0.1422632366,"remaining_time":0.3604337125},
{"learn":[4.505805643],"iteration":283,"passed_time":0.1425440301,"remaining_time":0.359371569},
{"learn":[4.501550352],"iteration":284,"passed_time":0.1427921151,"remaining_time":0.3582328502},
{"learn":[4.494692643],"iteration":285,"passed_time":0.1430964921,"remaining_time":0.357240893},
{"learn":[4.489330245],"iteration":286,"passed_time":0.143381619,"remaining_time":0.3562059037},
{"learn":[4.484826955],"iteration":287,"passed_time":0.1436842877,"remaining_time":0.3552194891},
{"learn":[4.478285428],"iteration":288,"passed_time":0.1439194976,"remaining_time":0.3540718436},
{"learn":[4.475311671],"iteration":289,"passed_time":0.1442380831,"remaining_time":0.3531346172},
{"learn":[4.471581298],"iteration":290,"passed_time":0.1445107099,"remaining_time":0.3520896677},
{"learn":[4.469164956],"iteration":291,"passed_time":0.1447780033,"remaining_time":0.3510370765},
{"learn":[4.462068024],"iteration":292,"passed_time":0.1450130049,"remaining_time":0.3499119264},
{"learn":[4.458540976],"iteration":293,"passed_time":0.1452865484,"remaining_time":0.3488853848},
{"learn":[4.455757458],"iteration":294,"passed_time":0.1455252583,"remaining_time":0.347780702},
{"learn":[4.453027414],"iteration":295,"passed_time":0.1458036768,"remaining_time":0.3467763124},
{"learn":[4.450659338],"iteration":296,"passed_time":0.14603197,"remaining_time":0.3456581646},
{"learn":[4.444696901],"iteration":297,"passed_time":0.1463022218,"remaining_time":0.3446448312},
{"learn":[4.442052813],"iteration":298,"passed_time":0.1465630568,"remaining_time":0.3436143908},
{"learn":[4.440036756],"iteration":299,"passed_time":0.1469086841,"remaining_time":0.3427869296},
{"learn":[4.435017051],"iteration":300,"passed_time":0.1472605198,"remaining_time":0.3419770875},
{"learn":[4.429962125],"iteration":301,"passed_time":0.1475356883,"remaining_time":0.3409930809},
{"learn":[4.427666256],"iteration":302,"passed_time":0.1478047318,"remaining_time":0.3399996635},
{"learn":[4.425030004],"iteration":303,"passed_time":0.1481517757,"remaining_time":0.3391895918},
{"learn":[4.422588771],"iteration":304,"passed_time":0.1484462777,"remaining_time":0.3382628295},
{"learn":[4.418936667],"iteration":305,"passed_time":0.1486825292,"remaining_time":0.3372080892},
{"learn":[4.416887976],"iteration":306,"passed_time":0.1489619478,"remaining_time":0.3362561231},
{"learn":[4.413773354],"iteration":307,"passed_time":0.1491758659,"remaining_time":0.335161361},
{"learn":[4.411129391],"iteration":308,"passed_time":0.1494616178,"remaining_time":0.3342329381},
{"learn":[4.40850819],"iteration":309,"passed_time":0.1497090777,"remaining_time":0.3332234311},
{"learn":[4.404880292],"iteration":310,"passed_time":0.1500014547,"remaining_time":0.3323183353},
{"learn":[4.404593827],"iteration":311,"passed_time":0.1502689981,"remaining_time":0.3313624061},
{"learn":[4.402139942],"iteration":312,"passed_time":0.1505524583,"remaining_time":0.3304458111},
{"learn":[4.400284725],"iteration":313,"passed_time":0.1508919606,"remaining_time":0.3296556846},
{"learn":[4.395805521],"iteration":314,"passed_time":0.151154879,"remaining_time":0.3287018797},
{"learn":[4.392838833],"iteration":315,"passed_time":0.151402964,"remaining_time":0.3277203398},
{"learn":[4.389213061],"iteration":316,"passed_time":0.1516999243,"remaining_time":0.3268487328},
{"learn":[4.3861981],"iteration":317,"passed_time":0.1519700511,"remaining_time":0.3259231913},
{"learn":[4.385054234],"iteration":318,"passed_time":0.1522003443,"remaining_time":0.3249167224},
{"learn":[4.379364607],"iteration":319,"passed_time":0.1524380125,"remaining_time":0.3239307766},
{"learn":[4.378387619],"iteration":320,"passed_time":0.1526945142,"remaining_time":0.3229893307},
{"learn":[4.375816727],"iteration":321,"passed_time":0.1529458076,"remaining_time":0.3220411725},
{"learn":[4.374600202],"iteration":322,"passed_time":0.1532047676,"remaining_time":0.3211133984},
{"learn":[4.37098897],"iteration":323,"passed_time":0.1534264774,"remaining_time":0.3201120331},
{"learn":[4.367418484],"iteration":324,"passed_time":0.1536966042,"remaining_time":0.3192160242},
{"learn":[4.363584638],"iteration":325,"passed_time":0.1539021889,"remaining_time":0.3181904151},
{"learn":[4.360770706],"iteration":326,"passed_time":0.1541571073,"remaining_time":0.3172713553},
{"learn":[4.358675808],"iteration":327,"passed_time":0.1544329424,"remaining_time":0.3163991992},
{"learn":[4.354228195],"iteration":328,"passed_time":0.1546788607,"remaining_time":0.3154696522},
{"learn":[4.353773425],"iteration":329,"passed_time":0.154921154,"remaining_time":0.3145368885},
{"learn":[4.351648009],"iteration":330,"passed_time":0.1552436562,"remaining_time":0.3137704108},
{"learn":[4.348209927],"iteration":331,"passed_time":0.1555212413,"remaining_time":0.3129162326},
{"learn":[4.345852733],"iteration":332,"passed_time":0.1558981188,"remaining_time":0.3122644002},
{"learn":[4.34237339],"iteration":333,"passed_time":0.1561355371,"remaining_time":0.3113361308},
{"learn":[4.340814362],"iteration":334,"passed_time":0.1563947471,"remaining_time":0.3104552443},
{"learn":[4.339707068],"iteration":335,"passed_time":0.1566263737,"remaining_time":0.309523548},
{"learn":[4.335430786],"iteration":336,"passed_time":0.1568857504,"remaining_time":0.3086506009},
{"learn":[4.33521887],"iteration":337,"passed_time":0.1571011685,"remaining_time":0.307695188},
{"learn":[4.328507238],"iteration":338,"passed_time":0.1573571702,"remaining_time":0.3068232729},
{"learn":[4.326140732],"iteration":339,"passed_time":0.1576394221,"remaining_time":0.306005937},
{"learn":[4.323785636],"iteration":340,"passed_time":0.1579162156,"remaining_time":0.3051811908},
{"learn":[4.320632534],"iteration":341,"passed_time":0.1581733423,"remaining_time":0.3043218106},
{"learn":[4.31973724],"iteration":342,"passed_time":0.1585341364,"remaining_time":0.3036645119},
{"learn":[4.318000924],"iteration":343,"passed_time":0.1588181382,"remaining_time":0.3028624962},
{"learn":[4.312713628],"iteration":344,"passed_time":0.1591553488,"remaining_time":0.3021645028},
{"learn":[4.308220789],"iteration":345,"passed_time":0.1594257256,"remaining_time":0.3013422675},
{"learn":[4.305890947],"iteration":346,"passed_time":0.1596342687,"remaining_time":0.3004068514},
{"learn":[4.305137856],"iteration":347,"passed_time":0.1598190616,"remaining_time":0.2994311153},
{"learn":[4.304787172],"iteration":348,"passed_time":0.1600560215,"remaining_time":0.2985572205},
{"learn":[4.30350134],"iteration":349,"passed_time":0.1603583568,"remaining_time":0.2978083769},
{"learn":[4.30293809],"iteration":350,"passed_time":0.1606084001,"remaining_time":0.2969653894},
{"learn":[4.299548459],"iteration":351,"passed_time":0.1608396517,"remaining_time":0.2960911769},
{"learn":[4.294768408],"iteration":352,"passed_time":0.1611095285,"remaining_time":0.295291402},
{"learn":[4.294581479],"iteration":353,"passed_time":0.1613627385,"remaining_time":0.2944642064},
{"learn":[4.292551604],"iteration":354,"passed_time":0.161639532,"remaining_time":0.2936830933},
{"learn":[4.288628894],"iteration":355,"passed_time":0.1618950753,"remaining_time":0.2928663723},
{"learn":[4.287802767],"iteration":356,"passed_time":0.1621747439,"remaining_time":0.2920962474},
{"learn":[4.284566905],"iteration":357,"passed_time":0.1625104544,"remaining_time":0.2914293624},
{"learn":[4.27890232],"iteration":358,"passed_time":0.1628162065,"remaining_time":0.290710831},
{"learn":[4.276938023],"iteration":359,"passed_time":0.1631341669,"remaining_time":0.2900162967},
{"learn":[4.273425094],"iteration":360,"passed_time":0.1633638351,"remaining_time":0.2891675641},
{"learn":[4.269726505],"iteration":361,"passed_time":0.1636082534,"remaining_time":0.2883482477},
{"learn":[4.265565857],"iteration":362,"passed_time":0.1638281298,"remaining_time":0.2874890323},
{"learn":[4.262117173],"iteration":363,"passed_time":0.1640883816,"remaining_time":0.2867038755},
{"learn":[4.259185148],"iteration":364,"passed_time":0.1643231748,"remaining_time":0.2858773041},
{"learn":[4.257668507],"iteration":365,"passed_time":0.1645694264,"remaining_time":0.2850738152},
{"learn":[4.253432436],"iteration":366,"passed_time":0.1648148447,"remaining_time":0.2842719257},
{"learn":[4.250216667],"iteration":367,"passed_time":0.1650361795,"remaining_time":0.2834316996},
{"learn":[4.24514828],"iteration":368,"passed_time":0.1654025153,"remaining_time":0.2828427836},
{"learn":[4.244015772],"iteration":369,"passed_time":0.1656461003,"remaining_time":0.2820460626},
{"learn":[4.240329192],"iteration":370,"passed_time":0.1659061437,"remaining_time":0.2812802274},
{"learn":[4.236718014],"iteration":371,"passed_time":0.1661706454,"remaining_time":0.2805246379},
{"learn":[4.233495944],"iteration":372,"passed_time":0.1664344388,"remaining_time":0.279770491},
{"learn":[4.230357491],"iteration":373,"passed_time":0.1666441902,"remaining_time":0.2789285109},
{"learn":[4.227381215],"iteration":374,"passed_time":0.1669186087,"remaining_time":0.2781976812},
{"learn":[4.226169067],"iteration":375,"passed_time":0.1671854021,"remaining_time":0.2774566248},
{"learn":[4.225963861],"iteration":376,"passed_time":0.1674523623,"remaining_time":0.2767183599},
{"learn":[4.224346548],"iteration":377,"passed_time":0.167764656,"remaining_time":0.2760571853},
{"learn":[4.222595381],"iteration":378,"passed_time":0.1680251994,"remaining_time":0.2753130576},
{"learn":[4.219700938],"iteration":379,"passed_time":0.1682915345,"remaining_time":0.2745809247},
{"learn":[4.216356207],"iteration":380,"passed_time":0.1685487445,"remaining_time":0.2738364117},
{"learn":[4.214326494],"iteration":381,"passed_time":0.1688450382,"remaining_time":0.2731576796},
{"learn":[4.212901398],"iteration":382,"passed_time":0.1690498729,"remaining_time":0.2723336072},
{"learn":[4.211331091],"iteration":383,"passed_time":0.1693760417,"remaining_time":0.2717074002},
{"learn":[4.208624791],"iteration":384,"passed_time":0.1696322934,"remaining_time":0.2709710661},
{"learn":[4.204659106],"iteration":385,"passed_time":0.1699509622,"remaining_time":0.2703365046},
{"learn":[4.202968852],"iteration":386,"passed_time":0.1702102139,"remaining_time":0.2696094603},
{"learn":[4.197261935],"iteration":387,"passed_time":0.1704593822,"remaining_time":0.2688689225},
{"learn":[4.196934403],"iteration":388,"passed_time":0.1707626342,"remaining_time":0.26821586},
{"learn":[4.192479929],"iteration":389,"passed_time":0.1709985525,"remaining_time":0.2674592744},
{"learn":[4.190243116],"iteration":390,"passed_time":0.1712598875,"remaining_time":0.2667449399},
{"learn":[4.185852431],"iteration":391,"passed_time":0.1714922224,"remaining_time":0.2659879368},
{"learn":[4.180967944],"iteration":392,"passed_time":0.1717276407,"remaining_time":0.2652383661},
{"learn":[4.178283162],"iteration":393,"passed_time":0.1719451421,"remaining_time":0.264463848},
{"learn":[4.176341157],"iteration":394,"passed_time":0.1722192689,"remaining_time":0.2637788802},
{"learn":[4.176041504],"iteration":395,"passed_time":0.1724945624,"remaining_time":0.2630977669},
{"learn":[4.175564513],"iteration":396,"passed_time":0.1728566065,"remaining_time":0.2625504627},
{"learn":[4.170830274],"iteration":397,"passed_time":0.1731071915,"remaining_time":0.2618355007},
{"learn":[4.167804808],"iteration":398,"passed_time":0.1733485681,"remaining_time":0.261108996},
{"learn":[4.165860548],"iteration":399,"passed_time":0.1736428617,"remaining_time":0.2604642926},
{"learn":[4.160950571],"iteration":400,"passed_time":0.1739118218,"remaining_time":0.2597834945},
{"learn":[4.158544115],"iteration":401,"passed_time":0.1741599068,"remaining_time":0.2590736922},
{"learn":[4.154448767],"iteration":402,"passed_time":0.1744034501,"remaining_time":0.2583594534},
{"learn":[4.15197457],"iteration":403,"passed_time":0.1746190765,"remaining_time":0.2576063604},
{"learn":[4.149562679],"iteration":404,"passed_time":0.1748264946,"remaining_time":0.2568438624},
{"learn":[4.149327961],"iteration":405,"passed_time":0.1750907047,"remaining_time":0.2561671886},
{"learn":[4.147444889],"iteration":406,"passed_time":0.1753355813,"remaining_time":0.2554643727},
{"learn":[4.147254809],"iteration":407,"passed_time":0.175600583,"remaining_time":0.2547930028},
{"learn":[4.144589165],"iteration":408,"passed_time":0.1758387096,"remaining_time":0.2540847858},
{"learn":[4.141691034],"iteration":409,"passed_time":0.1761505867,"remaining_time":0.2534849906},
{"learn":[4.138893468],"iteration":410,"passed_time":0.1764690471,"remaining_time":0.2528960311},
{"learn":[4.136964597],"iteration":411,"passed_time":0.1767260072,"remaining_time":0.2522206122},
{"learn":[4.133773523],"iteration":412,"passed_time":0.1770000923,"remaining_time":0.2515715598},
{"learn":[4.131363444],"iteration":413,"passed_time":0.1772337189,"remaining_time":0.2508670514},
{"learn":[4.130228592],"iteration":414,"passed_time":0.1774860956,"remaining_time":0.2501912432},
{"learn":[4.12884186],"iteration":415,"passed_time":0.1777119304,"remaining_time":0.24948021},
{"learn":[4.12413494],"iteration":416,"passed_time":0.1779354736,"remaining_time":0.2487683},
{"learn":[4.119422508],"iteration":417,"passed_time":0.1782943509,"remaining_time":0.2482471585},
{"learn":[4.117038244],"iteration":418,"passed_time":0.1786220614,"remaining_time":0.2476835745},
{"learn":[4.116067631],"iteration":419,"passed_time":0.1788990633,"remaining_time":0.2470510874},
{"learn":[4.110343455],"iteration":420,"passed_time":0.1791041063,"remaining_time":0.2463213244},
{"learn":[4.105604544],"iteration":421,"passed_time":0.1795739011,"remaining_time":0.2459566702},
{"learn":[4.103390131],"iteration":422,"passed_time":0.1799168617,"remaining_time":0.2454185088},
{"learn":[4.096724402],"iteration":423,"passed_time":0.1802385722,"remaining_time":0.2448523999},
{"learn":[4.093431279],"iteration":424,"passed_time":0.1804571153,"remaining_time":0.2441478619},
{"learn":[4.091412744],"iteration":425,"passed_time":0.1807322838,"remaining_time":0.2435219035},
{"learn":[4.091192901],"iteration":426,"passed_time":0.1809569103,"remaining_time":0.2428297649},
{"learn":[4.088994581],"iteration":427,"passed_time":0.1812025786,"remaining_time":0.2421679321},
{"learn":[4.087845355],"iteration":428,"passed_time":0.1814867471,"remaining_time":0.2415592835},
{"learn":[4.083650279],"iteration":429,"passed_time":0.1817495406,"remaining_time":0.2409238096},
{"learn":[4.079840652],"iteration":430,"passed_time":0.1820404175,"remaining_time":0.2403271405},
{"learn":[4.075707828],"iteration":431,"passed_time":0.1822681273,"remaining_time":0.2396488341},
{"learn":[4.071345409],"iteration":432,"passed_time":0.1825177123,"remaining_time":0.2390012538},
{"learn":[4.067460475],"iteration":433,"passed_time":0.1827308387,"remaining_time":0.2383079602},
{"learn":[4.064914749],"iteration":434,"passed_time":0.1829942988,"remaining_time":0.2376822502},
{"learn":[4.063823175],"iteration":435,"passed_time":0.1832914675,"remaining_time":0.2371018065},
{"learn":[4.058898471],"iteration":436,"passed_time":0.1835785527,"remaining_time":0.2365096686},
{"learn":[4.054120355],"iteration":437,"passed_time":0.1838254293,"remaining_time":0.2358673317},
{"learn":[4.052715901],"iteration":438,"passed_time":0.1840260973,"remaining_time":0.2351677463},
{"learn":[4.052114167],"iteration":439,"passed_time":0.1842918074,"remaining_time":0.2345532095},
{"learn":[4.051377267],"iteration":440,"passed_time":0.1845633092,"remaining_time":0.2339475961},
{"learn":[4.049275336],"iteration":441,"passed_time":0.1848069359,"remaining_time":0.2333083036},
{"learn":[4.047099198],"iteration":442,"passed_time":0.1851131046,"remaining_time":0.232749434},
{"learn":[4.044348685],"iteration":443,"passed_time":0.1854427318,"remaining_time":0.2322210785},
{"learn":[4.042822379],"iteration":444,"passed_time":0.1857976091,"remaining_time":0.231725108},
{"learn":[4.041258611],"iteration":445,"passed_time":0.1861279863,"remaining_time":0.2311993372},
{"learn":[4.040044254],"iteration":446,"passed_time":0.1864513218,"remaining_time":0.2306657292},
{"learn":[4.036860137],"iteration":447,"passed_time":0.1867055318,"remaining_time":0.2300478874},
{"learn":[4.036372284],"iteration":448,"passed_time":0.1869509501,"remaining_time":0.2294208764},
{"learn":[4.03368231],"iteration":449,"passed_time":0.1872061601,"remaining_time":0.228807529},
{"learn":[4.032439519],"iteration":450,"passed_time":0.1875973711,"remaining_time":0.2283613231},
{"learn":[4.032008634],"iteration":451,"passed_time":0.1878865813,"remaining_time":0.2277916959},
{"learn":[4.030034932],"iteration":452,"passed_time":0.1881415413,"remaining_time":0.2271819495},
{"learn":[4.028173412],"iteration":453,"passed_time":0.1883847096,"remaining_time":0.2265595847},
{"learn":[4.023806097],"iteration":454,"passed_time":0.1887702955,"remaining_time":0.2261094749},
{"learn":[4.020239186],"iteration":455,"passed_time":0.1890371306,"remaining_time":0.2255179804},
{"learn":[4.017384838],"iteration":456,"passed_time":0.1892838406,"remaining_time":0.2249039944},
{"learn":[4.016468229],"iteration":457,"passed_time":0.1895448007,"remaining_time":0.2243084759},
{"learn":[4.014530169],"iteration":458,"passed_time":0.1898478443,"remaining_time":0.223764017},
{"learn":[4.012884822],"iteration":459,"passed_time":0.1901168461,"remaining_time":0.2231806455},
{"learn":[4.008924707],"iteration":460,"passed_time":0.1904690151,"remaining_time":0.2226958767},
{"learn":[4.008286778],"iteration":461,"passed_time":0.1907591837,"remaining_time":0.2221394824},
{"learn":[4.006444202],"iteration":462,"passed_time":0.1910716025,"remaining_time":0.2216100443},
{"learn":[4.003284363],"iteration":463,"passed_time":0.1913468543,"remaining_time":0.2210386076},
{"learn":[3.999811484],"iteration":464,"passed_time":0.1916404396,"remaining_time":0.220489538},
{"learn":[3.997483319],"iteration":465,"passed_time":0.1918796912,"remaining_time":0.2198793028},
{"learn":[3.99708333],"iteration":466,"passed_time":0.1921651097,"remaining_time":0.2193233479},
{"learn":[3.995860263],"iteration":467,"passed_time":0.1923766528,"remaining_time":0.2186845711},
{"learn":[3.994131111],"iteration":468,"passed_time":0.1927051133,"remaining_time":0.2181799897},
{"learn":[3.993125499],"iteration":469,"passed_time":0.1929032396,"remaining_time":0.2175291851},
{"learn":[3.992954084],"iteration":470,"passed_time":0.193156658,"remaining_time":0.2169424036},
{"learn":[3.990635743],"iteration":471,"passed_time":0.1936869532,"remaining_time":0.2166667612},
{"learn":[3.986678254],"iteration":472,"passed_time":0.1939601217,"remaining_time":0.2161035605},
{"learn":[3.986393291],"iteration":473,"passed_time":0.1942222901,"remaining_time":0.2155293767},
{"learn":[3.986152671],"iteration":474,"passed_time":0.1945852091,"remaining_time":0.2150678627},
{"learn":[3.985596662],"iteration":475,"passed_time":0.1948687527,"remaining_time":0.2145193832},
{"learn":[3.983853457],"iteration":476,"passed_time":0.1951671713,"remaining_time":0.2139883241},
{"learn":[3.983263928],"iteration":477,"passed_time":0.1953786727,"remaining_time":0.2133633204},
{"learn":[3.980067202],"iteration":478,"passed_time":0.1956456329,"remaining_time":0.2128003648},
{"learn":[3.978115407],"iteration":479,"passed_time":0.1960311354,"remaining_time":0.2123670634},
{"learn":[3.972661644],"iteration":480,"passed_time":0.1963359291,"remaining_time":0.2118468757},
{"learn":[3.969938254],"iteration":481,"passed_time":0.1966078059,"remaining_time":0.2112922064},
{"learn":[3.968211434],"iteration":482,"passed_time":0.196876516,"remaining_time":0.2107353184},
{"learn":[3.966113368],"iteration":483,"passed_time":0.1971531845,"remaining_time":0.2101881058},
{"learn":[3.962246044],"iteration":484,"passed_time":0.1974724783,"remaining_time":0.2096872708},
{"learn":[3.961319703],"iteration":485,"passed_time":0.1977511885,"remaining_time":0.2091442611},
{"learn":[3.96078191],"iteration":486,"passed_time":0.1979752317,"remaining_time":0.2085447512},
{"learn":[3.958913633],"iteration":487,"passed_time":0.19822965,"remaining_time":0.2079786492},
{"learn":[3.957428286],"iteration":488,"passed_time":0.198431693,"remaining_time":0.2073590903},
{"learn":[3.952641965],"iteration":489,"passed_time":0.1987602369,"remaining_time":0.2068728996},
{"learn":[3.951486786],"iteration":490,"passed_time":0.1989895301,"remaining_time":0.2062844619},
{"learn":[3.94938344],"iteration":491,"passed_time":0.1993120322,"remaining_time":0.2057937243},
{"learn":[3.947297924],"iteration":492,"passed_time":0.1997274516,"remaining_time":0.2053992251},
{"learn":[3.946284886],"iteration":493,"passed_time":0.1999529948,"remaining_time":0.2048101526},
{"learn":[3.943288204],"iteration":494,"passed_time":0.2002139132,"remaining_time":0.2042586387},
{"learn":[3.943076488],"iteration":495,"passed_time":0.2004717482,"remaining_time":0.2037051635},
{"learn":[3.942347078],"iteration":496,"passed_time":0.2007148332,"remaining_time":0.2031379499},
{"learn":[3.940251541],"iteration":497,"passed_time":0.2009495014,"remaining_time":0.2025635536},
{"learn":[3.939011019],"iteration":498,"passed_time":0.2012604618,"remaining_time":0.202067117},
{"learn":[3.938760512],"iteration":499,"passed_time":0.2015395887,"remaining_time":0.2015395887},
{"learn":[3.934522727],"iteration":500,"passed_time":0.2018981327,"remaining_time":0.2010921521},
{"learn":[3.930091193],"iteration":501,"passed_time":0.2021974264,"remaining_time":0.2005862915},
{"learn":[3.927671752],"iteration":502,"passed_time":0.2024232612,"remaining_time":0.2000086696},
{"learn":[3.927280041],"iteration":503,"passed_time":0.2026482627,"remaining_time":0.1994316236},
{"learn":[3.925987561],"iteration":504,"passed_time":0.2028625558,"remaining_time":0.1988454755},
{"learn":[3.921645957],"iteration":505,"passed_time":0.2030866406,"remaining_time":0.1982703566},
{"learn":[3.920333743],"iteration":506,"passed_time":0.2033913926,"remaining_time":0.1977750623},
{"learn":[3.918659461],"iteration":507,"passed_time":0.2039901466,"remaining_time":0.1975652601},
{"learn":[3.916124385],"iteration":508,"passed_time":0.2043612324,"remaining_time":0.1971343126},
{"learn":[3.913849268],"iteration":509,"passed_time":0.2046528177,"remaining_time":0.196627217},
{"learn":[3.912826119],"iteration":510,"passed_time":0.2048574024,"remaining_time":0.1960377099},
{"learn":[3.910034145],"iteration":511,"passed_time":0.2050993623,"remaining_time":0.1954853297},
{"learn":[3.90792379],"iteration":512,"passed_time":0.2054349062,"remaining_time":0.1950230006},
{"learn":[3.907823851],"iteration":513,"passed_time":0.2057717834,"remaining_time":0.1945624256},
{"learn":[3.904527401],"iteration":514,"passed_time":0.2061192858,"remaining_time":0.1941123371},
{"learn":[3.903378283],"iteration":515,"passed_time":0.2063388289,"remaining_time":0.1935426224},
{"learn":[3.902170135],"iteration":516,"passed_time":0.2065760388,"remaining_time":0.1929907674},
{"learn":[3.899435429],"iteration":517,"passed_time":0.2067828735,"remaining_time":0.192411863},
{"learn":[3.897497505],"iteration":518,"passed_time":0.2070273751,"remaining_time":0.1918693014},
{"learn":[3.896426119],"iteration":519,"passed_time":0.2073179187,"remaining_time":0.1913703865},
{"learn":[3.896044669],"iteration":520,"passed_time":0.2075752954,"remaining_time":0.1908417783},
{"learn":[3.892795942],"iteration":521,"passed_time":0.2078228387,"remaining_time":0.1903052048},
{"learn":[3.892413888],"iteration":522,"passed_time":0.2080885072,"remaining_time":0.1897862675},
{"learn":[3.891738985],"iteration":523,"passed_time":0.2084260511,"remaining_time":0.1893335884},
{"learn":[3.88822057],"iteration":524,"passed_time":0.2087138447,"remaining_time":0.1888363356},
{"learn":[3.883837053],"iteration":525,"passed_time":0.2090054716,"remaining_time":0.1883433337},
{"learn":[3.881769742],"iteration":526,"passed_time":0.2093719324,"remaining_time":0.1879182619},
{"learn":[3.880356898],"iteration":527,"passed_time":0.2096292257,"remaining_time":0.187395823},
{"learn":[3.879250273],"iteration":528,"passed_time":0.2100104366,"remaining_time":0.1869847177},
{"learn":[3.877174493],"iteration":529,"passed_time":0.210327897,"remaining_time":0.1865171917},
{"learn":[3.875854201],"iteration":530,"passed_time":0.2106077322,"remaining_time":0.1860169989},
{"learn":[3.873189396],"iteration":531,"passed_time":0.2108523172,"remaining_time":0.1854866249},
{"learn":[3.871583368],"iteration":532,"passed_time":0.2110974022,"remaining_time":0.1849577614},
{"learn":[3.869622679],"iteration":533,"passed_time":0.2113843624,"remaining_time":0.1844665035},
{"learn":[3.866860164],"iteration":534,"passed_time":0.2116706976,"remaining_time":0.1839754662},
{"learn":[3.864498444],"iteration":535,"passed_time":0.2118868241,"remaining_time":0.1834244149},
{"learn":[3.861416322],"iteration":536,"passed_time":0.212231368,"remaining_time":0.1829853322},
{"learn":[3.860265769],"iteration":537,"passed_time":0.2124543695,"remaining_time":0.1824422281},
{"learn":[3.859328725],"iteration":538,"passed_time":0.2128013718,"remaining_time":0.1820063681},
{"learn":[3.858521278],"iteration":539,"passed_time":0.2130114982,"remaining_time":0.1814542392},
{"learn":[3.85599111],"iteration":540,"passed_time":0.2132499998,"remaining_time":0.180927449},
{"learn":[3.852379816],"iteration":541,"passed_time":0.2135636685,"remaining_time":0.1804652402},
{"learn":[3.851327537],"iteration":542,"passed_time":0.2137973368,"remaining_time":0.1799362484},
{"learn":[3.847854898],"iteration":543,"passed_time":0.2140644219,"remaining_time":0.1794363536},
{"learn":[3.847083414],"iteration":544,"passed_time":0.2143058818,"remaining_time":0.1789159197},
{"learn":[3.845397429],"iteration":545,"passed_time":0.2145265499,"remaining_time":0.1783792192},
{"learn":[3.841933528],"iteration":546,"passed_time":0.2148101768,"remaining_time":0.1778958137},
{"learn":[3.840996474],"iteration":547,"passed_time":0.2157951417,"remaining_time":0.1779916132},
{"learn":[3.838355966],"iteration":548,"passed_time":0.2160619351,"remaining_time":0.1774935023},
{"learn":[3.83342799],"iteration":549,"passed_time":0.2163635205,"remaining_time":0.1770246986},
{"learn":[3.828161535],"iteration":550,"passed_time":0.2165795636,"remaining_time":0.176486795},
{"learn":[3.823502399],"iteration":551,"passed_time":0.2168006067,"remaining_time":0.1759541156},
{"learn":[3.820068862],"iteration":552,"passed_time":0.2170771502,"remaining_time":0.1754674252},
{"learn":[3.817951642],"iteration":553,"passed_time":0.2173262352,"remaining_time":0.1749593879},
{"learn":[3.815785958],"iteration":554,"passed_time":0.2175887369,"remaining_time":0.1744630413},
{"learn":[3.81503012],"iteration":555,"passed_time":0.2179059057,"remaining_time":0.1740111909},
{"learn":[3.813529315],"iteration":556,"passed_time":0.2182489497,"remaining_time":0.1735804034},
{"learn":[3.808881326],"iteration":557,"passed_time":0.2185297432,"remaining_time":0.1731006209},
{"learn":[3.808740434],"iteration":558,"passed_time":0.218744828,"remaining_time":0.1725697122},
{"learn":[3.80714352],"iteration":559,"passed_time":0.2189619544,"remaining_time":0.1720415356},
{"learn":[3.80573346],"iteration":560,"passed_time":0.219203581,"remaining_time":0.17153364},
{"learn":[3.803370052],"iteration":561,"passed_time":0.2195442499,"remaining_time":0.1711038816},
{"learn":[3.803215211],"iteration":562,"passed_time":0.2197728348,"remaining_time":0.1705874401},
{"learn":[3.801309667],"iteration":563,"passed_time":0.2200321698,"remaining_time":0.1700957909},
{"learn":[3.800003847],"iteration":564,"passed_time":0.2203094633,"remaining_time":0.1696187904},
{"learn":[3.798026138],"iteration":565,"passed_time":0.2206791741,"remaining_time":0.1692133597},
{"learn":[3.794745847],"iteration":566,"passed_time":0.2209815928,"remaining_time":0.1687566661},
{"learn":[3.794312041],"iteration":567,"passed_time":0.2212840115,"remaining_time":0.1683005158},
{"learn":[3.792205926],"iteration":568,"passed_time":0.221617472,"remaining_time":0.1678684191},
{"learn":[3.788991061],"iteration":569,"passed_time":0.2218948489,"remaining_time":0.1673943597},
{"learn":[3.787391572],"iteration":570,"passed_time":0.222170934,"remaining_time":0.1669200187},
{"learn":[3.7826445],"iteration":571,"passed_time":0.2224188524,"remaining_time":0.1664252951},
{"learn":[3.781700331],"iteration":572,"passed_time":0.2226576039,"remaining_time":0.1659246019},
{"learn":[3.780045374],"iteration":573,"passed_time":0.2229438558,"remaining_time":0.1654600742},
{"learn":[3.775462644],"iteration":574,"passed_time":0.2232287744,"remaining_time":0.1649951811},
{"learn":[3.773711943],"iteration":575,"passed_time":0.2234579009,"remaining_time":0.1644898437},
{"learn":[3.772415806],"iteration":576,"passed_time":0.2237080693,"remaining_time":0.1640008896},
{"learn":[3.770170875],"iteration":577,"passed_time":0.2239964878,"remaining_time":0.1635406883},
{"learn":[3.765166479],"iteration":578,"passed_time":0.2242221977,"remaining_time":0.163035484},
{"learn":[3.763976102],"iteration":579,"passed_time":0.2244531159,"remaining_time":0.1625350149},
{"learn":[3.760761708],"iteration":580,"passed_time":0.2247049092,"remaining_time":0.1620505283},
{"learn":[3.758155662],"iteration":581,"passed_time":0.2249221606,"remaining_time":0.1615420329},
{"learn":[3.756844548],"iteration":582,"passed_time":0.2252026625,"remaining_time":0.1610797775},
{"learn":[3.753098923],"iteration":583,"passed_time":0.2254616226,"remaining_time":0.1606027996},
{"learn":[3.751618946],"iteration":584,"passed_time":0.225779958,"remaining_time":0.1601686882},
{"learn":[3.751398464],"iteration":585,"passed_time":0.2261080852,"remaining_time":0.1597418895},
{"learn":[3.749920103],"iteration":586,"passed_time":0.2263677536,"remaining_time":0.159267261},
{"learn":[3.748237465],"iteration":587,"passed_time":0.2266810473,"remaining_time":0.1588309379},
{"learn":[3.746021536],"iteration":588,"passed_time":0.226975091,"remaining_time":0.1583816},
{"learn":[3.74417648],"iteration":589,"passed_time":0.2272500094,"remaining_time":0.1579194981},
{"learn":[3.738788389],"iteration":590,"passed_time":0.2275579698,"remaining_time":0.1574808962},
{"learn":[3.736021611],"iteration":591,"passed_time":0.2278504301,"remaining_time":0.1570320532},
{"learn":[3.734546151],"iteration":592,"passed_time":0.2281162235,"remaining_time":0.156565435},
{"learn":[3.733527479],"iteration":593,"passed_time":0.2284308506,"remaining_time":0.156132871},
{"learn":[3.733026392],"iteration":594,"passed_time":0.2286952274,"remaining_time":0.1556664993},
{"learn":[3.730314752],"iteration":595,"passed_time":0.2289359373,"remaining_time":0.1551847629},
{"learn":[3.727342596],"iteration":596,"passed_time":0.2291608555,"remaining_time":0.1546931738},
{"learn":[3.725459604],"iteration":597,"passed_time":0.2294264406,"remaining_time":0.1542298146},
{"learn":[3.723158842],"iteration":598,"passed_time":0.2296411087,"remaining_time":0.1537330293},
{"learn":[3.722362756],"iteration":599,"passed_time":0.2298793186,"remaining_time":0.1532528791},
{"learn":[3.721443615],"iteration":600,"passed_time":0.2300889866,"remaining_time":0.1527545851},
{"learn":[3.720743486],"iteration":601,"passed_time":0.2303771135,"remaining_time":0.1523091216},
{"learn":[3.720215334],"iteration":602,"passed_time":0.2306303652,"remaining_time":0.1518412189},
{"learn":[3.719436563],"iteration":603,"passed_time":0.2308859503,"remaining_time":0.1513755568},
{"learn":[3.715046574],"iteration":604,"passed_time":0.2311019934,"remaining_time":0.1508847725},
{"learn":[3.71443396],"iteration":605,"passed_time":0.2313410783,"remaining_time":0.150409876},
{"learn":[3.712938941],"iteration":606,"passed_time":0.2316665804,"remaining_time":0.1499917069},
{"learn":[3.712814764],"iteration":607,"passed_time":0.2319333739,"remaining_time":0.1495359911},
{"learn":[3.71235348],"iteration":608,"passed_time":0.2322262092,"remaining_time":0.1490976154},
{"learn":[3.711223749],"iteration":609,"passed_time":0.2324526273,"remaining_time":0.1486172535},
{"learn":[3.710755648],"iteration":610,"passed_time":0.2326587537,"remaining_time":0.1481248039},
{"learn":[3.708668039],"iteration":611,"passed_time":0.232908172,"remaining_time":0.1476607365},
{"learn":[3.705623591],"iteration":612,"passed_time":0.2331793822,"remaining_time":0.1472111271},
{"learn":[3.704045802],"iteration":613,"passed_time":0.2334240088,"remaining_time":0.1467453866},
{"learn":[3.699915209],"iteration":614,"passed_time":0.2336695521,"remaining_time":0.1462809391},
{"learn":[3.696182221],"iteration":615,"passed_time":0.2339940959,"remaining_time":0.1458664494},
{"learn":[3.694263278],"iteration":616,"passed_time":0.2343417649,"remaining_time":0.1454666061},
{"learn":[3.693810229],"iteration":617,"passed_time":0.234812768,"remaining_time":0.1451431673},
{"learn":[3.690900932],"iteration":618,"passed_time":0.2351876038,"remaining_time":0.1447600599},
{"learn":[3.688020895],"iteration":619,"passed_time":0.2355103143,"remaining_time":0.1443450314},
{"learn":[3.685491894],"iteration":620,"passed_time":0.2358480249,"remaining_time":0.1439394548},
{"learn":[3.684328128],"iteration":621,"passed_time":0.2361389852,"remaining_time":0.1435056855},
{"learn":[3.680640153],"iteration":622,"passed_time":0.2363934452,"remaining_time":0.143050287},
{"learn":[3.678932783],"iteration":623,"passed_time":0.2368808234,"remaining_time":0.1427358808},
{"learn":[3.674167041],"iteration":624,"passed_time":0.2372436175,"remaining_time":0.1423461705},
{"learn":[3.672200976],"iteration":625,"passed_time":0.2375151193,"remaining_time":0.1419020042},
{"learn":[3.670606604],"iteration":626,"passed_time":0.2377684126,"remaining_time":0.1414475565},
{"learn":[3.665506042],"iteration":627,"passed_time":0.2380075392,"remaining_time":0.1409853576},
{"learn":[3.664214007],"iteration":628,"passed_time":0.2383527915,"remaining_time":0.1405864637},
{"learn":[3.66261643],"iteration":629,"passed_time":0.2385878764,"remaining_time":0.1401230385},
{"learn":[3.662118449],"iteration":630,"passed_time":0.2388472115,"remaining_time":0.1396745183},
{"learn":[3.660871366],"iteration":631,"passed_time":0.2390667546,"remaining_time":0.1392034267},
{"learn":[3.656695243],"iteration":632,"passed_time":0.2394400071,"remaining_time":0.1388222474},
{"learn":[3.654497801],"iteration":633,"passed_time":0.2396953421,"remaining_time":0.1383730208},
{"learn":[3.654189134],"iteration":634,"passed_time":0.2399217186,"remaining_time":0.1379077595},
{"learn":[3.653957699],"iteration":635,"passed_time":0.2401929287,"remaining_time":0.1374689089},
{"learn":[3.651920725],"iteration":636,"passed_time":0.240530431,"remaining_time":0.1370683618},
{"learn":[3.65106705],"iteration":637,"passed_time":0.2408651832,"remaining_time":0.1366664519},
{"learn":[3.650612844],"iteration":638,"passed_time":0.2411140182,"remaining_time":0.1362162137},
{"learn":[3.649884732],"iteration":639,"passed_time":0.2413503948,"remaining_time":0.1357595971},
{"learn":[3.646276182],"iteration":640,"passed_time":0.2416594802,"remaining_time":0.135344389},
{"learn":[3.645808194],"iteration":641,"passed_time":0.2419742739,"remaining_time":0.1349326948},
{"learn":[3.645042989],"iteration":642,"passed_time":0.2423209846,"remaining_time":0.1345390225},
{"learn":[3.639864499],"iteration":643,"passed_time":0.242742529,"remaining_time":0.1341868639},
{"learn":[3.637318478],"iteration":644,"passed_time":0.242993864,"remaining_time":0.1337408089},
{"learn":[3.636344905],"iteration":645,"passed_time":0.2432323239,"remaining_time":0.1332883014},
{"learn":[3.634754643],"iteration":646,"passed_time":0.2434667838,"remaining_time":0.1328342731},
{"learn":[3.630724975],"iteration":647,"passed_time":0.2438889116,"remaining_time":0.1324828656},
{"learn":[3.629408252],"iteration":648,"passed_time":0.2442682058,"remaining_time":0.1321080743},
{"learn":[3.62790646],"iteration":649,"passed_time":0.2445210408,"remaining_time":0.1316651758},
{"learn":[3.627388973],"iteration":650,"passed_time":0.2448531264,"remaining_time":0.1312653473},
{"learn":[3.625163557],"iteration":651,"passed_time":0.2450637111,"remaining_time":0.1308008765},
{"learn":[3.623701985],"iteration":652,"passed_time":0.2453152961,"remaining_time":0.1303589705},
{"learn":[3.622342639],"iteration":653,"passed_time":0.2455667561,"remaining_time":0.1299175804},
{"learn":[3.621130639],"iteration":654,"passed_time":0.2458859249,"remaining_time":0.1295124337},
{"learn":[3.619125665],"iteration":655,"passed_time":0.2461134681,"remaining_time":0.1290595016},
{"learn":[3.618878783],"iteration":656,"passed_time":0.2463685531,"remaining_time":0.1286216343},
{"learn":[3.616207429],"iteration":657,"passed_time":0.2466368466,"remaining_time":0.1281911877},
{"learn":[3.61206486],"iteration":658,"passed_time":0.2469145984,"remaining_time":0.1277661275},
{"learn":[3.611955873],"iteration":659,"passed_time":0.2471656001,"remaining_time":0.1273277334},
{"learn":[3.610713743],"iteration":660,"passed_time":0.2475638527,"remaining_time":0.1269654252},
{"learn":[3.610044025],"iteration":661,"passed_time":0.2478723964,"remaining_time":0.1265572054},
{"learn":[3.607342669],"iteration":662,"passed_time":0.2481231064,"remaining_time":0.1261198897},
{"learn":[3.602510618],"iteration":663,"passed_time":0.2483825248,"remaining_time":0.1256875427},
{"learn":[3.600492392],"iteration":664,"passed_time":0.2486545683,"remaining_time":0.1252620758},
{"learn":[3.597171065],"iteration":665,"passed_time":0.2488758614,"remaining_time":0.1248116182},
{"learn":[3.594358798],"iteration":666,"passed_time":0.2492000719,"remaining_time":0.1244132293},
{"learn":[3.593945251],"iteration":667,"passed_time":0.2495715744,"remaining_time":0.1240385669},
{"learn":[3.593607748],"iteration":668,"passed_time":0.2498802431,"remaining_time":0.1236328258},
{"learn":[3.592238714],"iteration":669,"passed_time":0.2501769951,"remaining_time":0.123221505},
{"learn":[3.590144654],"iteration":670,"passed_time":0.2504452052,"remaining_time":0.1227965313},
{"learn":[3.587151536],"iteration":671,"passed_time":0.2507275821,"remaining_time":0.1223789389},
{"learn":[3.586070865],"iteration":672,"passed_time":0.2510241674,"remaining_time":0.1219686519},
{"learn":[3.585102746],"iteration":673,"passed_time":0.2512497105,"remaining_time":0.1215243407},
{"learn":[3.584362847],"iteration":674,"passed_time":0.2514667536,"remaining_time":0.1210765851},
{"learn":[3.581407561],"iteration":675,"passed_time":0.2517586722,"remaining_time":0.1206653991},
{"learn":[3.57919422],"iteration":676,"passed_time":0.2519798404,"remaining_time":0.1202208101},
{"learn":[3.577632204],"iteration":677,"passed_time":0.2522277587,"remaining_time":0.1197895845},
{"learn":[3.573911195],"iteration":678,"passed_time":0.2525533858,"remaining_time":0.119395636},
{"learn":[3.573408216],"iteration":679,"passed_time":0.2528017625,"remaining_time":0.1189655353},
{"learn":[3.571076482],"iteration":680,"passed_time":0.2530913894,"remaining_time":0.1185552911},
{"learn":[3.568177107],"iteration":681,"passed_time":0.2533586412,"remaining_time":0.1181349676},
{"learn":[3.564824621],"iteration":682,"passed_time":0.2536026845,"remaining_time":0.1177043206},
{"learn":[3.562475026],"iteration":683,"passed_time":0.253888228,"remaining_time":0.1172933919},
{"learn":[3.561226889],"iteration":684,"passed_time":0.2541997718,"remaining_time":0.1168947856},
{"learn":[3.559383467],"iteration":685,"passed_time":0.2544698986,"remaining_time":0.1164774754},
{"learn":[3.555209766],"iteration":686,"passed_time":0.2547292336,"remaining_time":0.116055677},
{"learn":[3.55345383],"iteration":687,"passed_time":0.254979652,"remaining_time":0.1156303073},
{"learn":[3.552300968],"iteration":688,"passed_time":0.2553342793,"remaining_time":0.1152524831},
{"learn":[3.551253986],"iteration":689,"passed_time":0.2557564488,"remaining_time":0.1149050712},
{"learn":[3.549807725],"iteration":690,"passed_time":0.2560229089,"remaining_time":0.1144878131},
{"learn":[3.547992926],"iteration":691,"passed_time":0.2562505354,"remaining_time":0.1140537065},
{"learn":[3.545438607],"iteration":692,"passed_time":0.2565946627,"remaining_time":0.1136718058},
{"learn":[3.543313763],"iteration":693,"passed_time":0.2571494997,"remaining_time":0.1133829206},
{"learn":[3.542962896],"iteration":694,"passed_time":0.2574056264,"remaining_time":0.1129621814},
{"learn":[3.539800465],"iteration":695,"passed_time":0.2577412953,"remaining_time":0.1125766577},
{"learn":[3.53953187],"iteration":696,"passed_time":0.2579909636,"remaining_time":0.1121538909},
{"learn":[3.536332425],"iteration":697,"passed_time":0.2584084664,"remaining_time":0.1118042362},
{"learn":[3.534993327],"iteration":698,"passed_time":0.2586858432,"remaining_time":0.1113940469},
{"learn":[3.531637011],"iteration":699,"passed_time":0.259057179,"remaining_time":0.1110245053},
{"learn":[3.531040284],"iteration":700,"passed_time":0.259297639,"remaining_time":0.1105991356},
{"learn":[3.529973872],"iteration":701,"passed_time":0.2595384322,"remaining_time":0.1101744342},
{"learn":[3.527325183],"iteration":702,"passed_time":0.2597836005,"remaining_time":0.1097521044},
{"learn":[3.527200815],"iteration":703,"passed_time":0.2600360606,"remaining_time":0.1093333436},
{"learn":[3.523459911],"iteration":704,"passed_time":0.2603377709,"remaining_time":0.108935663},
{"learn":[3.522729934],"iteration":705,"passed_time":0.260652523,"remaining_time":0.1085436852},
{"learn":[3.522260582],"iteration":706,"passed_time":0.2609222331,"remaining_time":0.1081332593},
{"learn":[3.518641591],"iteration":707,"passed_time":0.261150693,"remaining_time":0.107706218},
{"learn":[3.516856405],"iteration":708,"passed_time":0.2614098613,"remaining_time":0.1072923408},
{"learn":[3.515083413],"iteration":709,"passed_time":0.2616521546,"remaining_time":0.1068720068},
{"learn":[3.514671214],"iteration":710,"passed_time":0.2619247814,"remaining_time":0.1064645033},
{"learn":[3.512617621],"iteration":711,"passed_time":0.2621896999,"remaining_time":0.1060542606},
{"learn":[3.510747971],"iteration":712,"passed_time":0.2624927019,"remaining_time":0.1056597552},
{"learn":[3.508149266],"iteration":713,"passed_time":0.2628274124,"remaining_time":0.1052782072},
{"learn":[3.504557165],"iteration":714,"passed_time":0.2631704147,"remaining_time":0.1049000954},
{"learn":[3.501367208],"iteration":715,"passed_time":0.2633892078,"remaining_time":0.1044728143},
{"learn":[3.497593362],"iteration":716,"passed_time":0.2636335011,"remaining_time":0.1040561797},
{"learn":[3.496291169],"iteration":717,"passed_time":0.2638900862,"remaining_time":0.1036448528},
{"learn":[3.49330374],"iteration":718,"passed_time":0.264166838,"remaining_time":0.1032418379},
{"learn":[3.490044385],"iteration":719,"passed_time":0.2644470482,"remaining_time":0.1028405187},
{"learn":[3.488891789],"iteration":720,"passed_time":0.2647096749,"remaining_time":0.1024327314},
{"learn":[3.486869081],"iteration":721,"passed_time":0.2649560932,"remaining_time":0.1020191051},
{"learn":[3.486303638],"iteration":722,"passed_time":0.2652373868,"remaining_time":0.1016193031},
{"learn":[3.486035862],"iteration":723,"passed_time":0.2656598062,"remaining_time":0.1012736278},
{"learn":[3.482668951],"iteration":724,"passed_time":0.2660021002,"remaining_time":0.1008973483},
{"learn":[3.47820549],"iteration":725,"passed_time":0.2662458518,"remaining_time":0.1004839716},
{"learn":[3.474392283],"iteration":726,"passed_time":0.26648227,"remaining_time":0.1000683077},
{"learn":[3.472268163],"iteration":727,"passed_time":0.2667153549,"remaining_time":0.09965189085},
{"learn":[3.471209164],"iteration":728,"passed_time":0.266926648,"remaining_time":0.099227876},
{"learn":[3.470049971],"iteration":729,"passed_time":0.2672526085,"remaining_time":0.09884685519},
{"learn":[3.469078654],"iteration":730,"passed_time":0.2674936518,"remaining_time":0.09843473642},
{"learn":[3.468643292],"iteration":731,"passed_time":0.267732445,"remaining_time":0.09802226129},
{"learn":[3.468134848],"iteration":732,"passed_time":0.2680489054,"remaining_time":0.09763855082},
{"learn":[3.467820182],"iteration":733,"passed_time":0.2682766153,"remaining_time":0.09722286058},
{"learn":[3.465776156],"iteration":734,"passed_time":0.2685406587,"remaining_time":0.09682078171},
{"learn":[3.463037608],"iteration":735,"passed_time":0.2695777073,"remaining_time":0.09669635152},
{"learn":[3.45965637],"iteration":736,"passed_time":0.2698220422,"remaining_time":0.09628656323},
{"learn":[3.457275091],"iteration":737,"passed_time":0.2701578361,"remaining_time":0.0959096925},
{"learn":[3.455522955],"iteration":738,"passed_time":0.270389671,"remaining_time":0.09549621668},
{"learn":[3.451270508],"iteration":739,"passed_time":0.2706415477,"remaining_time":0.0950902735},
{"learn":[3.450978947],"iteration":740,"passed_time":0.2709275496,"remaining_time":0.09469667387},
{"learn":[3.450608492],"iteration":741,"passed_time":0.2711427177,"remaining_time":0.09427873471},
{"learn":[3.448122004],"iteration":742,"passed_time":0.2713732609,"remaining_time":0.09386665954},
{"learn":[3.445646714],"iteration":743,"passed_time":0.2716079291,"remaining_time":0.09345649173},
{"learn":[3.44411263],"iteration":744,"passed_time":0.2719205145,"remaining_time":0.09307346469},
{"learn":[3.443264164],"iteration":745,"passed_time":0.2721831829,"remaining_time":0.09267363064},
{"learn":[3.439521363],"iteration":746,"passed_time":0.2724647681,"remaining_time":0.09228057072},
{"learn":[3.436809225],"iteration":747,"passed_time":0.2726875613,"remaining_time":0.09186800192},
{"learn":[3.435509465],"iteration":748,"passed_time":0.2729133961,"remaining_time":0.09145695917},
{"learn":[3.434450277],"iteration":749,"passed_time":0.2732456483,"remaining_time":0.09108188276},
{"learn":[3.431786753],"iteration":750,"passed_time":0.2735572337,"remaining_time":0.09070006816},
{"learn":[3.430150302],"iteration":751,"passed_time":0.2738650691,"remaining_time":0.09031720363},
{"learn":[3.42696281],"iteration":752,"passed_time":0.2741011123,"remaining_time":0.08991098903},
{"learn":[3.426870334],"iteration":753,"passed_time":0.2751732444,"remaining_time":0.08977800813},
{"learn":[3.425200309],"iteration":754,"passed_time":0.2754886632,"remaining_time":0.08939698342},
{"learn":[3.423383783],"iteration":755,"passed_time":0.2757153314,"remaining_time":0.0889874879},
{"learn":[3.422752979],"iteration":756,"passed_time":0.2759714997,"remaining_time":0.08858794509},
{"learn":[3.420845924],"iteration":757,"passed_time":0.2762050429,"remaining_time":0.08818155725},
{"learn":[3.418917862],"iteration":758,"passed_time":0.2764442945,"remaining_time":0.0877774374},
{"learn":[3.417095735],"iteration":759,"passed_time":0.2766774628,"remaining_time":0.08737183034},
{"learn":[3.414391848],"iteration":760,"passed_time":0.2768888392,"remaining_time":0.08695983253},
{"learn":[3.41426711],"iteration":761,"passed_time":0.2771382575,"remaining_time":0.08656024315},
{"learn":[3.411976013],"iteration":762,"passed_time":0.2773299254,"remaining_time":0.08614310921},
{"learn":[3.408614844],"iteration":763,"passed_time":0.2775692603,"remaining_time":0.08574128984},
{"learn":[3.407906721],"iteration":764,"passed_time":0.2778658456,"remaining_time":0.085357482},
{"learn":[3.407494015],"iteration":765,"passed_time":0.2781059306,"remaining_time":0.08495664198},
{"learn":[3.406287128],"iteration":766,"passed_time":0.2784202243,"remaining_time":0.08457876437},
{"learn":[3.404600442],"iteration":767,"passed_time":0.2786626009,"remaining_time":0.08417932737},
{"learn":[3.404012662],"iteration":768,"passed_time":0.2789963532,"remaining_time":0.08380774718},
{"learn":[3.400398762],"iteration":769,"passed_time":0.2792573966,"remaining_time":0.08341454702},
{"learn":[3.399737714],"iteration":770,"passed_time":0.2794924398,"remaining_time":0.0830139672},
{"learn":[3.399185251],"iteration":771,"passed_time":0.2798339837,"remaining_time":0.0826452698},
{"learn":[3.397245411],"iteration":772,"passed_time":0.2802145279,"remaining_time":0.08228809552},
{"learn":[3.396229831],"iteration":773,"passed_time":0.2806350724,"remaining_time":0.08194254051},
{"learn":[3.394002836],"iteration":774,"passed_time":0.2809177409,"remaining_time":0.08155676349},
{"learn":[3.389617243],"iteration":775,"passed_time":0.2811266173,"remaining_time":0.08114995139},
{"learn":[3.385426488],"iteration":776,"passed_time":0.2813731189,"remaining_time":0.08075444726},
{"learn":[3.385072258],"iteration":777,"passed_time":0.2816157039,"remaining_time":0.08035820856},
{"learn":[3.383842366],"iteration":778,"passed_time":0.2818442054,"remaining_time":0.07995836893},
{"learn":[3.380110746],"iteration":779,"passed_time":0.2821417074,"remaining_time":0.07957843029},
{"learn":[3.378595218],"iteration":780,"passed_time":0.2823572505,"remaining_time":0.07917572069},
{"learn":[3.377371219],"iteration":781,"passed_time":0.2826220856,"remaining_time":0.07878723102},
{"learn":[3.375814782],"iteration":782,"passed_time":0.2828932957,"remaining_time":0.07840082397},
{"learn":[3.374195887],"iteration":783,"passed_time":0.2831809226,"remaining_time":0.07801923378},
{"learn":[3.373704309],"iteration":784,"passed_time":0.283482633,"remaining_time":0.07764174024},
{"learn":[3.372971757],"iteration":785,"passed_time":0.2837375096,"remaining_time":0.07725168838},
{"learn":[3.371565136],"iteration":786,"passed_time":0.2839716362,"remaining_time":0.07685636405},
{"learn":[3.3700309],"iteration":787,"passed_time":0.2842020127,"remaining_time":0.07646043997},
{"learn":[3.368186663],"iteration":788,"passed_time":0.2845643901,"remaining_time":0.07610023615},
{"learn":[3.366710398],"iteration":789,"passed_time":0.2848109751,"remaining_time":0.07570924655},
{"learn":[3.364598042],"iteration":790,"passed_time":0.285102602,"remaining_time":0.07533052317},
{"learn":[3.36348442],"iteration":791,"passed_time":0.2853596454,"remaining_time":0.07494293718},
{"learn":[3.362001759],"iteration":792,"passed_time":0.2856083971,"remaining_time":0.07455351601},
{"learn":[3.361580401],"iteration":793,"passed_time":0.2858377736,"remaining_time":0.07415942237},
{"learn":[3.359543675],"iteration":794,"passed_time":0.2860815252,"remaining_time":0.0737694499},
{"learn":[3.35766119],"iteration":795,"passed_time":0.2863554437,"remaining_time":0.07338757602},
{"learn":[3.354592969],"iteration":796,"passed_time":0.2866014453,"remaining_time":0.07299886249},
{"learn":[3.350985986],"iteration":797,"passed_time":0.2868948223,"remaining_time":0.07262249887},
{"learn":[3.349589624],"iteration":798,"passed_time":0.2872149077,"remaining_time":0.0722530619},
{"learn":[3.349110856],"iteration":799,"passed_time":0.2875526183,"remaining_time":0.07188815458},
{"learn":[3.345315441],"iteration":800,"passed_time":0.2877771198,"remaining_time":0.07149518957},
{"learn":[3.34397474],"iteration":801,"passed_time":0.2881842059,"remaining_time":0.07114772164},
{"learn":[3.343800902],"iteration":802,"passed_time":0.2885454166,"remaining_time":0.07078885064},
{"learn":[3.342329465],"iteration":803,"passed_time":0.28881246,"remaining_time":0.07040701762},
{"learn":[3.34220347],"iteration":804,"passed_time":0.2891572123,"remaining_time":0.07004429367},
{"learn":[3.341279219],"iteration":805,"passed_time":0.2893984222,"remaining_time":0.0696566922},
{"learn":[3.337329521],"iteration":806,"passed_time":0.2895982152,"remaining_time":0.06925954838},
{"learn":[3.336708453],"iteration":807,"passed_time":0.2898962172,"remaining_time":0.06888622983},
{"learn":[3.333252703],"iteration":808,"passed_time":0.2901276354,"remaining_time":0.06849737746},
{"learn":[3.332186769],"iteration":809,"passed_time":0.2903792204,"remaining_time":0.0681136443},
{"learn":[3.330594851],"iteration":810,"passed_time":0.2906482639,"remaining_time":0.06773430564},
{"learn":[3.327867442],"iteration":811,"passed_time":0.2910132246,"remaining_time":0.0673774461},
{"learn":[3.327563111],"iteration":812,"passed_time":0.2912423095,"remaining_time":0.0669893135},
{"learn":[3.326308994],"iteration":813,"passed_time":0.2915322281,"remaining_time":0.06661547227},
{"learn":[3.326249879],"iteration":814,"passed_time":0.2917730214,"remaining_time":0.06623068583},
{"learn":[3.322336238],"iteration":815,"passed_time":0.2919866478,"remaining_time":0.06584012646},
{"learn":[3.320491154],"iteration":816,"passed_time":0.2922104409,"remaining_time":0.06545227747},
{"learn":[3.320434271],"iteration":817,"passed_time":0.2925217763,"remaining_time":0.0650843072},
{"learn":[3.319609638],"iteration":818,"passed_time":0.2927611946,"remaining_time":0.06470058147},
{"learn":[3.316182682],"iteration":819,"passed_time":0.2930088629,"remaining_time":0.06431901868},
{"learn":[3.313126612],"iteration":820,"passed_time":0.293271448,"remaining_time":0.06394103433},
{"learn":[3.311222803],"iteration":821,"passed_time":0.2934841994,"remaining_time":0.06355253953},
{"learn":[3.309627335],"iteration":822,"passed_time":0.2938048682,"remaining_time":0.06318768125},
{"learn":[3.307974895],"iteration":823,"passed_time":0.2941050785,"remaining_time":0.06281856046},
{"learn":[3.307321505],"iteration":824,"passed_time":0.2943899554,"remaining_time":0.06244635418},
{"learn":[3.306759087],"iteration":825,"passed_time":0.2946513321,"remaining_time":0.06206940895},
{"learn":[3.30484037],"iteration":826,"passed_time":0.2949814593,"remaining_time":0.06170712511},
{"learn":[3.30201994],"iteration":827,"passed_time":0.2952722113,"remaining_time":0.06133673954},
{"learn":[3.299302297],"iteration":828,"passed_time":0.2955456297,"remaining_time":0.06096297067},
{"learn":[3.298132671],"iteration":829,"passed_time":0.2958832987,"remaining_time":0.06060260334},
{"learn":[3.296976183],"iteration":830,"passed_time":0.2962389677,"remaining_time":0.06024595131},
{"learn":[3.293144745],"iteration":831,"passed_time":0.2966972207,"remaining_time":0.05991001572},
{"learn":[3.290284404],"iteration":832,"passed_time":0.2970402647,"remaining_time":0.05955068932},
{"learn":[3.288285745],"iteration":833,"passed_time":0.2972657245,"remaining_time":0.05916799792},
{"learn":[3.286662667],"iteration":834,"passed_time":0.2975403513,"remaining_time":0.05879539877},
{"learn":[3.285692682],"iteration":835,"passed_time":0.2978502701,"remaining_time":0.05842995728},
{"learn":[3.284565611],"iteration":836,"passed_time":0.298138147,"remaining_time":0.05806035598},
{"learn":[3.283897383],"iteration":837,"passed_time":0.2984076904,"remaining_time":0.05768740555},
{"learn":[3.280712855],"iteration":838,"passed_time":0.2986259419,"remaining_time":0.05730485893},
{"learn":[3.280468341],"iteration":839,"passed_time":0.2988844019,"remaining_time":0.05693036227},
{"learn":[3.277814895],"iteration":840,"passed_time":0.2991891539,"remaining_time":0.05656489355},
{"learn":[3.276316385],"iteration":841,"passed_time":0.2994090304,"remaining_time":0.05618364229},
{"learn":[3.27557063],"iteration":842,"passed_time":0.2997321576,"remaining_time":0.05582200325},
{"learn":[3.27499628],"iteration":843,"passed_time":0.300000576,"remaining_time":0.05545034343},
{"learn":[3.273569958],"iteration":844,"passed_time":0.3003234115,"remaining_time":0.0550889098},
{"learn":[3.269665595],"iteration":845,"passed_time":0.3005542463,"remaining_time":0.05471082026},
{"learn":[3.267984685],"iteration":846,"passed_time":0.300804498,"remaining_time":0.05433658583},
{"learn":[3.267702508],"iteration":847,"passed_time":0.3010870416,"remaining_time":0.05396843198},
{"learn":[3.266671924],"iteration":848,"passed_time":0.3013685851,"remaining_time":0.05360030194},
{"learn":[3.265359825],"iteration":849,"passed_time":0.3016864622,"remaining_time":0.05323878745},
{"learn":[3.2618983],"iteration":850,"passed_time":0.3019746308,"remaining_time":0.0528721739},
{"learn":[3.260456253],"iteration":851,"passed_time":0.3023838835,"remaining_time":0.05252677789},
{"learn":[3.258389147],"iteration":852,"passed_time":0.3027307608,"remaining_time":0.05217048281},
{"learn":[3.258108469],"iteration":853,"passed_time":0.3029749708,"remaining_time":0.05179665776},
{"learn":[3.256424936],"iteration":854,"passed_time":0.3031949306,"remaining_time":0.05141902331},
{"learn":[3.254817983],"iteration":855,"passed_time":0.3034395988,"remaining_time":0.05104591382},
{"learn":[3.253898449],"iteration":856,"passed_time":0.3037195174,"remaining_time":0.05067898598},
{"learn":[3.253023652],"iteration":857,"passed_time":0.3040153527,"remaining_time":0.0503148952},
{"learn":[3.252845542],"iteration":858,"passed_time":0.3043034379,"remaining_time":0.04994969121},
{"learn":[3.252316026],"iteration":859,"passed_time":0.3045867315,"remaining_time":0.04958388652},
{"learn":[3.24975301],"iteration":860,"passed_time":0.3048450248,"remaining_time":0.04921423746},
{"learn":[3.249151075],"iteration":861,"passed_time":0.3050711097,"remaining_time":0.04883969041},
{"learn":[3.246257135],"iteration":862,"passed_time":0.305322403,"remaining_time":0.04846948924},
{"learn":[3.243826471],"iteration":863,"passed_time":0.3055744464,"remaining_time":0.04809968137},
{"learn":[3.243190653],"iteration":864,"passed_time":0.3058104896,"remaining_time":0.04772764867},
{"learn":[3.24008797],"iteration":865,"passed_time":0.3060814914,"remaining_time":0.04736133932},
{"learn":[3.240036811],"iteration":866,"passed_time":0.3063185346,"remaining_time":0.04699004049},
{"learn":[3.238676314],"iteration":867,"passed_time":0.3065583696,"remaining_time":0.04661947556},
{"learn":[3.237848782],"iteration":868,"passed_time":0.306775121,"remaining_time":0.0462457317},
{"learn":[3.236405498],"iteration":869,"passed_time":0.3070762063,"remaining_time":0.04588495037},
{"learn":[3.233378068],"iteration":870,"passed_time":0.3073035412,"remaining_time":0.04551338325},
{"learn":[3.233169169],"iteration":871,"passed_time":0.3075858347,"remaining_time":0.04515021427},
{"learn":[3.232434885],"iteration":872,"passed_time":0.3078499615,"remaining_time":0.04478458775},
{"learn":[3.229978115],"iteration":873,"passed_time":0.3081267966,"remaining_time":0.0444210256},
{"learn":[3.229648848],"iteration":874,"passed_time":0.3083977568,"remaining_time":0.0440568224},
{"learn":[3.227208761],"iteration":875,"passed_time":0.3086468834,"remaining_time":0.04368974149},
{"learn":[3.226258869],"iteration":876,"passed_time":0.308937927,"remaining_time":0.04332880847},
{"learn":[3.225331995],"iteration":877,"passed_time":0.3093096378,"remaining_time":0.04297924353},
{"learn":[3.221968268],"iteration":878,"passed_time":0.3095693896,"remaining_time":0.04261421631},
{"learn":[3.221166317],"iteration":879,"passed_time":0.3098385997,"remaining_time":0.04225071814},
{"learn":[3.220047503],"iteration":880,"passed_time":0.3101366017,"remaining_time":0.04189132304},
{"learn":[3.21982781],"iteration":881,"passed_time":0.3103949784,"remaining_time":0.04152676581},
{"learn":[3.216693405],"iteration":882,"passed_time":0.3106390217,"remaining_time":0.04116054987},
{"learn":[3.214798761],"iteration":883,"passed_time":0.3109206485,"remaining_time":0.04079954212},
{"learn":[3.214395085],"iteration":884,"passed_time":0.3111661918,"remaining_time":0.04043402493},
{"learn":[3.213470696],"iteration":885,"passed_time":0.3114629438,"remaining_time":0.04007536749},
{"learn":[3.211595017],"iteration":886,"passed_time":0.31189528,"remaining_time":0.03973412248},
{"learn":[3.210965255],"iteration":887,"passed_time":0.3128113694,"remaining_time":0.03945368623},
{"learn":[3.209413583],"iteration":888,"passed_time":0.3133036227,"remaining_time":0.03911890002},
{"learn":[3.208331683],"iteration":889,"passed_time":0.3136242082,"remaining_time":0.03876254258},
{"learn":[3.207110711],"iteration":890,"passed_time":0.3138859182,"remaining_time":0.03839906295},
{"learn":[3.204519413],"iteration":891,"passed_time":0.3141299615,"remaining_time":0.03803367247},
{"learn":[3.201421296],"iteration":892,"passed_time":0.3144927139,"remaining_time":0.03768277759},
{"learn":[3.200691259],"iteration":893,"passed_time":0.3147742575,"remaining_time":0.0373222274},
{"learn":[3.200485067],"iteration":894,"passed_time":0.3150669261,"remaining_time":0.03696315893},
{"learn":[3.197467568],"iteration":895,"passed_time":0.3153154694,"remaining_time":0.03659911698},
{"learn":[3.195838544],"iteration":896,"passed_time":0.315554971,"remaining_time":0.03623429433},
{"learn":[3.195671746],"iteration":897,"passed_time":0.3158500563,"remaining_time":0.0358760643},
{"learn":[3.194213094],"iteration":898,"passed_time":0.3160819328,"remaining_time":0.03551087343},
{"learn":[3.192884691],"iteration":899,"passed_time":0.3163557263,"remaining_time":0.03515063626},
{"learn":[3.188364239],"iteration":900,"passed_time":0.3166191447,"remaining_time":0.03478945097},
{"learn":[3.185219478],"iteration":901,"passed_time":0.3168518963,"remaining_time":0.03442515059},
{"learn":[3.184120387],"iteration":902,"passed_time":0.3172050653,"remaining_time":0.03407407678},
{"learn":[3.183725321],"iteration":903,"passed_time":0.3175385675,"remaining_time":0.03372090982},
{"learn":[3.181264554],"iteration":904,"passed_time":0.3177744441,"remaining_time":0.03335753833},
{"learn":[3.180741589],"iteration":905,"passed_time":0.3179982372,"remaining_time":0.03299319459},
{"learn":[3.179782639],"iteration":906,"passed_time":0.3182782807,"remaining_time":0.03263492846},
{"learn":[3.176377564],"iteration":907,"passed_time":0.3185706577,"remaining_time":0.03227808426},
{"learn":[3.174078182],"iteration":908,"passed_time":0.3188810347,"remaining_time":0.0319231839},
{"learn":[3.171242379],"iteration":909,"passed_time":0.3191537449,"remaining_time":0.03156465609},
{"learn":[3.170421012],"iteration":910,"passed_time":0.3200409174,"remaining_time":0.03126634649},
{"learn":[3.170087224],"iteration":911,"passed_time":0.3204146283,"remaining_time":0.03091720097},
{"learn":[3.167303059],"iteration":912,"passed_time":0.3206680883,"remaining_time":0.03055654291},
{"learn":[3.16705966],"iteration":913,"passed_time":0.3208737146,"remaining_time":0.03019161866},
{"learn":[3.165667683],"iteration":914,"passed_time":0.3211394247,"remaining_time":0.02983262416},
{"learn":[3.164689733],"iteration":915,"passed_time":0.3213694679,"remaining_time":0.02947056256},
{"learn":[3.163311455],"iteration":916,"passed_time":0.3216613865,"remaining_time":0.0291143894},
{"learn":[3.159425016],"iteration":917,"passed_time":0.3219023048,"remaining_time":0.02875380065},
{"learn":[3.159327058],"iteration":918,"passed_time":0.3221843067,"remaining_time":0.02839709341},
{"learn":[3.15819426],"iteration":919,"passed_time":0.3224032665,"remaining_time":0.02803506665},
{"learn":[3.157086603],"iteration":920,"passed_time":0.3226970184,"remaining_time":0.02767976597},
{"learn":[3.153354154],"iteration":921,"passed_time":0.3229082282,"remaining_time":0.02731761583},
{"learn":[3.153261317],"iteration":922,"passed_time":0.3231471881,"remaining_time":0.02695810778},
{"learn":[3.153168454],"iteration":923,"passed_time":0.3234236066,"remaining_time":0.02660194167},
{"learn":[3.152080399],"iteration":924,"passed_time":0.3237536088,"remaining_time":0.0262502926},
{"learn":[3.151635144],"iteration":925,"passed_time":0.3240149022,"remaining_time":0.02589319953},
{"learn":[3.147762655],"iteration":926,"passed_time":0.324282154,"remaining_time":0.02553678235},
{"learn":[3.147172317],"iteration":927,"passed_time":0.3245938227,"remaining_time":0.02518400348},
{"learn":[3.146254125],"iteration":928,"passed_time":0.3248296159,"remaining_time":0.02482551424},
{"learn":[3.144869828],"iteration":929,"passed_time":0.3251219512,"remaining_time":0.02447154471},
{"learn":[3.143466218],"iteration":930,"passed_time":0.3253650361,"remaining_time":0.02411405746},
{"learn":[3.141919643],"iteration":931,"passed_time":0.3256316213,"remaining_time":0.02375853031},
{"learn":[3.141054135],"iteration":932,"passed_time":0.325843831,"remaining_time":0.02339928904},
{"learn":[3.139390417],"iteration":933,"passed_time":0.3261227912,"remaining_time":0.02304507946},
{"learn":[3.139025283],"iteration":934,"passed_time":0.3263629178,"remaining_time":0.02268833118},
{"learn":[3.137824183],"iteration":935,"passed_time":0.3266302946,"remaining_time":0.02233369535},
{"learn":[3.135620453],"iteration":936,"passed_time":0.3268852546,"remaining_time":0.02197841093},
{"learn":[3.13443178],"iteration":937,"passed_time":0.3271279229,"remaining_time":0.02162252795},
{"learn":[3.132765713],"iteration":938,"passed_time":0.3274362999,"remaining_time":0.02127115473},
{"learn":[3.131434124],"iteration":939,"passed_time":0.3277723021,"remaining_time":0.02092163631},
{"learn":[3.128384262],"iteration":940,"passed_time":0.3280233871,"remaining_time":0.02056682236},
{"learn":[3.128120455],"iteration":941,"passed_time":0.3283293475,"remaining_time":0.02021560738},
{"learn":[3.126314615],"iteration":942,"passed_time":0.3285950576,"remaining_time":0.01986205544},
{"learn":[3.125409666],"iteration":943,"passed_time":0.3288496426,"remaining_time":0.01950802965},
{"learn":[3.123072589],"iteration":944,"passed_time":0.3291688947,"remaining_time":0.019157978},
{"learn":[3.122921099],"iteration":945,"passed_time":0.3294495216,"remaining_time":0.01880578665},
{"learn":[3.122182662],"iteration":946,"passed_time":0.3297353152,"remaining_time":0.01845403559},
{"learn":[3.120040951],"iteration":947,"passed_time":0.3300246921,"remaining_time":0.01810262024},
{"learn":[3.118767799],"iteration":948,"passed_time":0.3302873605,"remaining_time":0.0177499003},
{"learn":[3.118203218],"iteration":949,"passed_time":0.3306384462,"remaining_time":0.01740202348},
{"learn":[3.116343362],"iteration":950,"passed_time":0.3308975729,"remaining_time":0.01704940176},
{"learn":[3.11480829],"iteration":951,"passed_time":0.3311472412,"remaining_time":0.01669649956},
{"learn":[3.112607903],"iteration":952,"passed_time":0.3314012012,"remaining_time":0.01634402566},
{"learn":[3.111661241],"iteration":953,"passed_time":0.3316255361,"remaining_time":0.01599032983},
{"learn":[3.110249676],"iteration":954,"passed_time":0.3318448709,"remaining_time":0.01563666931},
{"learn":[3.107333579],"iteration":955,"passed_time":0.3321052893,"remaining_time":0.01528518068},
{"learn":[3.107149851],"iteration":956,"passed_time":0.3329904201,"remaining_time":0.014961952},
{"learn":[3.106867336],"iteration":957,"passed_time":0.3332506719,"remaining_time":0.01461015472},
{"learn":[3.10364681],"iteration":958,"passed_time":0.3335590489,"remaining_time":0.01426060584},
{"learn":[3.102703811],"iteration":959,"passed_time":0.3339199263,"remaining_time":0.01391333026},
{"learn":[3.101469264],"iteration":960,"passed_time":0.3341403444,"remaining_time":0.01356032615},
{"learn":[3.09863569],"iteration":961,"passed_time":0.3344333464,"remaining_time":0.01321046483},
{"learn":[3.09645939],"iteration":962,"passed_time":0.3347067649,"remaining_time":0.01285996916},
{"learn":[3.096240186],"iteration":963,"passed_time":0.3350707256,"remaining_time":0.01251301465},
{"learn":[3.094838828],"iteration":964,"passed_time":0.3355198536,"remaining_time":0.01216911386},
{"learn":[3.094176802],"iteration":965,"passed_time":0.3357659802,"remaining_time":0.01181785024},
{"learn":[3.093182279],"iteration":966,"passed_time":0.3360112735,"remaining_time":0.01146677562},
{"learn":[3.090150687],"iteration":967,"passed_time":0.3362463168,"remaining_time":0.01111558072},
{"learn":[3.088612829],"iteration":968,"passed_time":0.3365013185,"remaining_time":0.01076526406},
{"learn":[3.087153684],"iteration":969,"passed_time":0.3368147789,"remaining_time":0.01041695192},
{"learn":[3.085866843],"iteration":970,"passed_time":0.3370959474,"remaining_time":0.01006774714},
{"learn":[3.082669094],"iteration":971,"passed_time":0.3373690325,"remaining_time":0.009718449497},
{"learn":[3.081047548],"iteration":972,"passed_time":0.3376437427,"remaining_time":0.0093693536},
{"learn":[3.079684322],"iteration":973,"passed_time":0.3378746609,"remaining_time":0.009019241462},
{"learn":[3.07613431],"iteration":974,"passed_time":0.3381391627,"remaining_time":0.00867023494},
{"learn":[3.074005935],"iteration":975,"passed_time":0.3384118728,"remaining_time":0.00832160343},
{"learn":[3.072988853],"iteration":976,"passed_time":0.3386599578,"remaining_time":0.007972547624},
{"learn":[3.072344268],"iteration":977,"passed_time":0.3389463347,"remaining_time":0.007624559676},
{"learn":[3.070654438],"iteration":978,"passed_time":0.3393301289,"remaining_time":0.007278787239},
{"learn":[3.069724506],"iteration":979,"passed_time":0.3395392553,"remaining_time":0.006929372557},
{"learn":[3.067763166],"iteration":980,"passed_time":0.3398837576,"remaining_time":0.006582865845},
{"learn":[3.066737893],"iteration":981,"passed_time":0.3403060937,"remaining_time":0.006237789905},
{"learn":[3.065248174],"iteration":982,"passed_time":0.3405611371,"remaining_time":0.005889663612},
{"learn":[3.063186837],"iteration":983,"passed_time":0.3409713898,"remaining_time":0.005544250241},
{"learn":[3.062880371],"iteration":984,"passed_time":0.3412873086,"remaining_time":0.005197268658},
{"learn":[3.061288645],"iteration":985,"passed_time":0.3415301019,"remaining_time":0.004849311791},
{"learn":[3.059970575],"iteration":986,"passed_time":0.3424205244,"remaining_time":0.004510098093},
{"learn":[3.059576341],"iteration":987,"passed_time":0.3426911096,"remaining_time":0.004162240197},
{"learn":[3.058175919],"iteration":988,"passed_time":0.3429900282,"remaining_time":0.003814853701},
{"learn":[3.056830702],"iteration":989,"passed_time":0.3432874052,"remaining_time":0.003467549547},
{"learn":[3.056336579],"iteration":990,"passed_time":0.3435401152,"remaining_time":0.003119940501},
{"learn":[3.055810414],"iteration":991,"passed_time":0.3437920752,"remaining_time":0.002772516736},
{"learn":[3.055476518],"iteration":992,"passed_time":0.3440405352,"remaining_time":0.00242526057},
{"learn":[3.053331734],"iteration":993,"passed_time":0.344308537,"remaining_time":0.002078321149},
{"learn":[3.050890374],"iteration":994,"passed_time":0.3447183314,"remaining_time":0.001732252921},
{"learn":[3.04972623],"iteration":995,"passed_time":0.3450400835,"remaining_time":0.001385703147},
{"learn":[3.047217327],"iteration":996,"passed_time":0.3452864601,"remaining_time":0.001038976309},
{"learn":[3.047155483],"iteration":997,"passed_time":0.3455607536,"remaining_time":0.0006925065203},
{"learn":[3.04430671],"iteration":998,"passed_time":0.3458746724,"remaining_time":0.0003462208933},
{"learn":[3.042664195],"iteration":999,"passed_time":0.3461912995,"remaining_time":0}
]}